{"match_id": 6514176015, "barracks_status_dire": 63, "barracks_status_radiant": 0, "chat": null, "cluster": 251, "cosmetics": null, "dire_score": 38, "dire_team_id": null, "draft_timings": null, "duration": 2124, "engine": 1, "first_blood_time": 159, "game_mode": 22, "human_players": 10, "leagueid": 0, "lobby_type": 7, "match_seq_num": 5441613999, "negative_votes": 0, "objectives": null, "picks_bans": [{"is_pick": true, "hero_id": 27, "team": 1, "order": 0}, {"is_pick": true, "hero_id": 26, "team": 1, "order": 1}, {"is_pick": true, "hero_id": 30, "team": 0, "order": 2}, {"is_pick": true, "hero_id": 85, "team": 0, "order": 3}, {"is_pick": true, "hero_id": 75, "team": 0, "order": 4}, {"is_pick": true, "hero_id": 81, "team": 0, "order": 5}, {"is_pick": true, "hero_id": 35, "team": 1, "order": 6}, {"is_pick": true, "hero_id": 17, "team": 1, "order": 7}, {"is_pick": true, "hero_id": 70, "team": 1, "order": 8}, {"is_pick": true, "hero_id": 6, "team": 0, "order": 9}, {"is_pick": false, "hero_id": 136, "team": 0, "order": 10}, {"is_pick": false, "hero_id": 1, "team": 0, "order": 11}], "positive_votes": 0, "radiant_gold_adv": null, "radiant_score": 24, "radiant_team_id": null, "radiant_win": false, "radiant_xp_adv": null, "skill": null, "start_time": 1649388055, "teamfights": null, "tower_status_dire": 1974, "tower_status_radiant": 0, "version": null, "replay_salt": 1168160766, "series_id": 0, "series_type": 0, "players": [{"match_id": 6514176015, "player_slot": 0, "ability_targets": null, "ability_upgrades_arr": [5019, 343, 343, 5019, 343, 5022, 5019, 343, 5019, 5632, 5632, 5022, 6209, 5632, 486, 5632, 5022, 6202], "ability_uses": null, "account_id": null, "actions": null, "additional_units": null, "assists": 8, "backpack_0": 0, "backpack_1": 326, "backpack_2": 0, "backpack_3": null, "buyback_log": null, "camps_stacked": null, "connection_log": null, "creeps_stacked": null, "damage": null, "damage_inflictor": null, "damage_inflictor_received": null, "damage_taken": null, "damage_targets": null, "deaths": 9, "denies": 7, "dn_t": null, "firstblood_claimed": null, "gold": 495, "gold_per_min": 437, "gold_reasons": null, "gold_spent": 13945, "gold_t": null, "hero_damage": 11607, "hero_healing": 0, "hero_hits": null, "hero_id": 6, "item_0": 147, "item_1": 102, "item_2": 88, "item_3": 75, "item_4": 29, "item_5": 152, "item_neutral": 675, "item_uses": null, "kill_streaks": null, "killed": null, "killed_by": null, "kills": 3, "kills_log": null, "lane_pos": null, "last_hits": 221, "leaver_status": 0, "level": 20, "lh_t": null, "life_state": null, "max_hero_hit": null, "multi_kills": null, "net_worth": 13125, "obs": null, "obs_left_log": null, "obs_log": null, "obs_placed": null, "party_id": 0, "party_size": 1, "performance_others": null, "permanent_buffs": [{"permanent_buff": 12, "stack_count": 0}], "pings": null, "pred_vict": null, "purchase": null, "purchase_log": null, "randomed": null, "repicked": null, "roshans_killed": null, "rune_pickups": null, "runes": null, "runes_log": null, "sen": null, "sen_left_log": null, "sen_log": null, "sen_placed": null, "stuns": null, "teamfight_participation": null, "times": null, "tower_damage": 888, "towers_killed": null, "xp_per_min": 537, "xp_reasons": null, "xp_t": null, "radiant_win": false, "start_time": 1649388055, "duration": 2124, "cluster": 251, "lobby_type": 7, "game_mode": 22, "is_contributor": false, "patch": 50, "region": 15, "isRadiant": true, "win": 0, "lose": 1, "total_gold": 15469, "total_xp": 19009, "kills_per_min": 0.08474576271186442, "kda": 1, "abandons": 0, "rank_tier": null, "cosmetics": [], "benchmarks": {"gold_per_min": {"raw": 437, "pct": 0.2065359477124183}, "xp_per_min": {"raw": 537, "pct": 0.17712418300653596}, "kills_per_min": {"raw": 0.0847457627118644, "pct": 0.14313725490196078}, "last_hits_per_min": {"raw": 6.242937853107345, "pct": 0.4045751633986928}, "hero_damage_per_min": {"raw": 327.8813559322034, "pct": 0.10457516339869281}, "hero_healing_per_min": {"raw": 0, "pct": 0.9705882352941176}, "tower_damage": {"raw": 888, "pct": 0.25882352941176473}, "stuns_per_min": {"raw": 0, "pct": 0.9856209150326798}, "lhten": {}}}, {"match_id": 6514176015, "player_slot": 1, "ability_targets": null, "ability_upgrades_arr": [5378, 5377, 5379, 5377, 5379, 5380, 5377, 5377, 5378, 5906, 5378, 5380, 5379, 5378, 5379, 5943], "ability_uses": null, "account_id": null, "actions": null, "additional_units": null, "assists": 11, "backpack_0": 216, "backpack_1": 0, "backpack_2": 38, "backpack_3": null, "buyback_log": null, "camps_stacked": null, "connection_log": null, "creeps_stacked": null, "damage": null, "damage_inflictor": null, "damage_inflictor_received": null, "damage_taken": null, "damage_targets": null, "deaths": 6, "denies": 0, "dn_t": null, "firstblood_claimed": null, "gold": 649, "gold_per_min": 267, "gold_reasons": null, "gold_spent": 9555, "gold_t": null, "hero_damage": 13363, "hero_healing": 0, "hero_hits": null, "hero_id": 75, "item_0": 63, "item_1": 77, "item_2": 596, "item_3": 534, "item_4": 236, "item_5": 0, "item_neutral": 359, "item_uses": null, "kill_streaks": null, "killed": null, "killed_by": null, "kills": 2, "kills_log": null, "lane_pos": null, "last_hits": 52, "leaver_status": 0, "level": 16, "lh_t": null, "life_state": null, "max_hero_hit": null, "multi_kills": null, "net_worth": 8594, "obs": null, "obs_left_log": null, "obs_log": null, "obs_placed": null, "party_id": 1, "party_size": 1, "performance_others": null, "permanent_buffs": [{"permanent_buff": 3, "stack_count": 12}, {"permanent_buff": 6, "stack_count": 2}], "pings": null, "pred_vict": null, "purchase": null, "purchase_log": null, "randomed": null, "repicked": null, "roshans_killed": null, "rune_pickups": null, "runes": null, "runes_log": null, "sen": null, "sen_left_log": null, "sen_log": null, "sen_placed": null, "stuns": null, "teamfight_participation": null, "times": null, "tower_damage": 425, "towers_killed": null, "xp_per_min": 369, "xp_reasons": null, "xp_t": null, "radiant_win": false, "start_time": 1649388055, "duration": 2124, "cluster": 251, "lobby_type": 7, "game_mode": 22, "is_contributor": false, "patch": 50, "region": 15, "isRadiant": true, "win": 0, "lose": 1, "total_gold": 9451, "total_xp": 13062, "kills_per_min": 0.05649717514124294, "kda": 1, "abandons": 0, "rank_tier": null, "cosmetics": [], "benchmarks": {"gold_per_min": {"raw": 267, "pct": 0.13443072702331962}, "xp_per_min": {"raw": 369, "pct": 0.13580246913580246}, "kills_per_min": {"raw": 0.05649717514124294, "pct": 0.1111111111111111}, "last_hits_per_min": {"raw": 1.4689265536723164, "pct": 0.26474622770919065}, "hero_damage_per_min": {"raw": 377.4858757062147, "pct": 0.17078189300411523}, "hero_healing_per_min": {"raw": 0, "pct": 0.7558299039780522}, "tower_damage": {"raw": 425, "pct": 0.3724279835390947}, "stuns_per_min": {"raw": 0, "pct": 0.8525377229080933}, "lhten": {}}}, {"match_id": 6514176015, "player_slot": 2, "ability_targets": null, "ability_upgrades_arr": [5138, 5140, 5138, 5140, 5138, 5141, 5140, 5138, 5140, 417, 5139, 5141, 5139, 5139, 6524, 5139, 5141, 555], "ability_uses": null, "account_id": null, "actions": null, "additional_units": null, "assists": 9, "backpack_0": 0, "backpack_1": 0, "backpack_2": 0, "backpack_3": null, "buyback_log": null, "camps_stacked": null, "connection_log": null, "creeps_stacked": null, "damage": null, "damage_inflictor": null, "damage_inflictor_received": null, "damage_taken": null, "damage_targets": null, "deaths": 7, "denies": 0, "dn_t": null, "firstblood_claimed": null, "gold": 1979, "gold_per_min": 311, "gold_reasons": null, "gold_spent": 7870, "gold_t": null, "hero_damage": 18465, "hero_healing": 775, "hero_hits": null, "hero_id": 30, "item_0": 254, "item_1": 36, "item_2": 60, "item_3": 218, "item_4": 180, "item_5": 0, "item_neutral": 574, "item_uses": null, "kill_streaks": null, "killed": null, "killed_by": null, "kills": 8, "kills_log": null, "lane_pos": null, "last_hits": 42, "leaver_status": 0, "level": 20, "lh_t": null, "life_state": null, "max_hero_hit": null, "multi_kills": null, "net_worth": 8479, "obs": null, "obs_left_log": null, "obs_log": null, "obs_placed": null, "party_id": 2, "party_size": 1, "performance_others": null, "permanent_buffs": [{"permanent_buff": 12, "stack_count": 0}], "pings": null, "pred_vict": null, "purchase": null, "purchase_log": null, "randomed": null, "repicked": null, "roshans_killed": null, "rune_pickups": null, "runes": null, "runes_log": null, "sen": null, "sen_left_log": null, "sen_log": null, "sen_placed": null, "stuns": null, "teamfight_participation": null, "times": null, "tower_damage": 0, "towers_killed": null, "xp_per_min": 516, "xp_reasons": null, "xp_t": null, "radiant_win": false, "start_time": 1649388055, "duration": 2124, "cluster": 251, "lobby_type": 7, "game_mode": 22, "is_contributor": false, "patch": 50, "region": 15, "isRadiant": true, "win": 0, "lose": 1, "total_gold": 11009, "total_xp": 18266, "kills_per_min": 0.22598870056497175, "kda": 2, "abandons": 0, "rank_tier": null, "cosmetics": [], "benchmarks": {"gold_per_min": {"raw": 311, "pct": 0.4028892455858748}, "xp_per_min": {"raw": 516, "pct": 0.5730337078651685}, "kills_per_min": {"raw": 0.22598870056497175, "pct": 0.7279293739967897}, "last_hits_per_min": {"raw": 1.1864406779661019, "pct": 0.434991974317817}, "hero_damage_per_min": {"raw": 521.6101694915254, "pct": 0.6067415730337079}, "hero_healing_per_min": {"raw": 21.892655367231637, "pct": 0.21508828250401285}, "tower_damage": {"raw": 0, "pct": 0.2174959871589085}, "stuns_per_min": {"raw": 0, "pct": 0}, "lhten": {}}}, {"match_id": 6514176015, "player_slot": 3, "ability_targets": null, "ability_upgrades_arr": [5444, 5442, 5444, 5443, 5444, 5447, 5442, 5444, 5442, 807, 5443, 5447, 5442, 5443, 5443, 6155, 5447], "ability_uses": null, "account_id": 176062543, "actions": null, "additional_units": null, "assists": 9, "backpack_0": 0, "backpack_1": 0, "backpack_2": 0, "backpack_3": null, "buyback_log": null, "camps_stacked": null, "connection_log": null, "creeps_stacked": null, "damage": null, "damage_inflictor": null, "damage_inflictor_received": null, "damage_taken": null, "damage_targets": null, "deaths": 6, "denies": 1, "dn_t": null, "firstblood_claimed": null, "gold": 1138, "gold_per_min": 310, "gold_reasons": null, "gold_spent": 9990, "gold_t": null, "hero_damage": 9055, "hero_healing": 270, "hero_hits": null, "hero_id": 85, "item_0": 127, "item_1": 36, "item_2": 37, "item_3": 12, "item_4": 29, "item_5": 242, "item_neutral": 354, "item_uses": null, "kill_streaks": null, "killed": null, "killed_by": null, "kills": 3, "kills_log": null, "lane_pos": null, "last_hits": 106, "leaver_status": 0, "level": 19, "lh_t": null, "life_state": null, "max_hero_hit": null, "multi_kills": null, "net_worth": 10863, "obs": null, "obs_left_log": null, "obs_log": null, "obs_placed": null, "party_id": 3, "party_size": 1, "performance_others": null, "permanent_buffs": [{"permanent_buff": 6, "stack_count": 1}, {"permanent_buff": 12, "stack_count": 0}], "pings": null, "pred_vict": null, "purchase": null, "purchase_log": null, "randomed": null, "repicked": null, "roshans_killed": null, "rune_pickups": null, "runes": null, "runes_log": null, "sen": null, "sen_left_log": null, "sen_log": null, "sen_placed": null, "stuns": null, "teamfight_participation": null, "times": null, "tower_damage": 0, "towers_killed": null, "xp_per_min": 476, "xp_reasons": null, "xp_t": null, "personaname": "OG PAPAYITA", "name": null, "last_login": null, "radiant_win": false, "start_time": 1649388055, "duration": 2124, "cluster": 251, "lobby_type": 7, "game_mode": 22, "is_contributor": false, "patch": 50, "region": 15, "isRadiant": true, "win": 0, "lose": 1, "total_gold": 10974, "total_xp": 16850, "kills_per_min": 0.08474576271186442, "kda": 1, "abandons": 0, "rank_tier": 24, "cosmetics": [], "benchmarks": {"gold_per_min": {"raw": 310, "pct": 0.3277591973244147}, "xp_per_min": {"raw": 476, "pct": 0.4439799331103679}, "kills_per_min": {"raw": 0.0847457627118644, "pct": 0.2265886287625418}, "last_hits_per_min": {"raw": 2.994350282485876, "pct": 0.8219063545150501}, "hero_damage_per_min": {"raw": 255.7909604519774, "pct": 0.20234113712374582}, "hero_healing_per_min": {"raw": 7.627118644067796, "pct": 0.0794314381270903}, "tower_damage": {"raw": 0, "pct": 0.15217391304347827}, "stuns_per_min": {"raw": 0, "pct": 0.9113712374581939}, "lhten": {}}}, {"match_id": 6514176015, "player_slot": 4, "ability_targets": null, "ability_upgrades_arr": [5426, 5428, 5427, 5427, 5426, 5428, 5427, 5427, 5429, 5426, 6618, 5429, 5426, 5428, 5428, 5928, 5429], "ability_uses": null, "account_id": null, "actions": null, "additional_units": null, "assists": 8, "backpack_0": 3, "backpack_1": 0, "backpack_2": 0, "backpack_3": null, "buyback_log": null, "camps_stacked": null, "connection_log": null, "creeps_stacked": null, "damage": null, "damage_inflictor": null, "damage_inflictor_received": null, "damage_taken": null, "damage_targets": null, "deaths": 10, "denies": 18, "dn_t": null, "firstblood_claimed": null, "gold": 1113, "gold_per_min": 467, "gold_reasons": null, "gold_spent": 13715, "gold_t": null, "hero_damage": 10940, "hero_healing": 0, "hero_hits": null, "hero_id": 81, "item_0": 154, "item_1": 485, "item_2": 36, "item_3": 73, "item_4": 63, "item_5": 114, "item_neutral": 686, "item_uses": null, "kill_streaks": null, "killed": null, "killed_by": null, "kills": 5, "kills_log": null, "lane_pos": null, "last_hits": 241, "leaver_status": 0, "level": 19, "lh_t": null, "life_state": null, "max_hero_hit": null, "multi_kills": null, "net_worth": 14568, "obs": null, "obs_left_log": null, "obs_log": null, "obs_placed": null, "party_id": 4, "party_size": 1, "performance_others": null, "permanent_buffs": [], "pings": null, "pred_vict": null, "purchase": null, "purchase_log": null, "randomed": null, "repicked": null, "roshans_killed": null, "rune_pickups": null, "runes": null, "runes_log": null, "sen": null, "sen_left_log": null, "sen_log": null, "sen_placed": null, "stuns": null, "teamfight_participation": null, "times": null, "tower_damage": 678, "towers_killed": null, "xp_per_min": 487, "xp_reasons": null, "xp_t": null, "radiant_win": false, "start_time": 1649388055, "duration": 2124, "cluster": 251, "lobby_type": 7, "game_mode": 22, "is_contributor": false, "patch": 50, "region": 15, "isRadiant": true, "win": 0, "lose": 1, "total_gold": 16531, "total_xp": 17239, "kills_per_min": 0.14124293785310735, "kda": 1, "abandons": 0, "rank_tier": null, "cosmetics": [], "benchmarks": {"gold_per_min": {"raw": 467, "pct": 0.32701062215478}, "xp_per_min": {"raw": 487, "pct": 0.15022761760242792}, "kills_per_min": {"raw": 0.14124293785310735, "pct": 0.2109256449165402}, "last_hits_per_min": {"raw": 6.807909604519774, "pct": 0.7412746585735963}, "hero_damage_per_min": {"raw": 309.03954802259886, "pct": 0.09408194233687406}, "hero_healing_per_min": {"raw": 0, "pct": 0.9711684370257967}, "tower_damage": {"raw": 678, "pct": 0.21851289833080426}, "stuns_per_min": {"raw": 0, "pct": 0}, "lhten": {}}}, {"match_id": 6514176015, "player_slot": 128, "ability_targets": null, "ability_upgrades_arr": [5080, 5079, 5080, 5079, 5080, 5081, 5080, 5079, 5079, 468, 5078, 5081, 5078, 5078, 6295, 5078, 5081], "ability_uses": null, "account_id": null, "actions": null, "additional_units": null, "assists": 21, "backpack_0": 0, "backpack_1": 21, "backpack_2": 22, "backpack_3": null, "buyback_log": null, "camps_stacked": null, "connection_log": null, "creeps_stacked": null, "damage": null, "damage_inflictor": null, "damage_inflictor_received": null, "damage_taken": null, "damage_targets": null, "deaths": 7, "denies": 6, "dn_t": null, "firstblood_claimed": null, "gold": 1446, "gold_per_min": 335, "gold_reasons": null, "gold_spent": 10205, "gold_t": null, "hero_damage": 5672, "hero_healing": 0, "hero_hits": null, "hero_id": 27, "item_0": 43, "item_1": 34, "item_2": 1, "item_3": 23, "item_4": 214, "item_5": 232, "item_neutral": 290, "item_uses": null, "kill_streaks": null, "killed": null, "killed_by": null, "kills": 1, "kills_log": null, "lane_pos": null, "last_hits": 46, "leaver_status": 0, "level": 18, "lh_t": null, "life_state": null, "max_hero_hit": null, "multi_kills": null, "net_worth": 10246, "obs": null, "obs_left_log": null, "obs_log": null, "obs_placed": null, "party_id": 5, "party_size": 1, "performance_others": null, "permanent_buffs": [], "pings": null, "pred_vict": null, "purchase": null, "purchase_log": null, "randomed": null, "repicked": null, "roshans_killed": null, "rune_pickups": null, "runes": null, "runes_log": null, "sen": null, "sen_left_log": null, "sen_log": null, "sen_placed": null, "stuns": null, "teamfight_participation": null, "times": null, "tower_damage": 3971, "towers_killed": null, "xp_per_min": 432, "xp_reasons": null, "xp_t": null, "radiant_win": false, "start_time": 1649388055, "duration": 2124, "cluster": 251, "lobby_type": 7, "game_mode": 22, "is_contributor": false, "patch": 50, "region": 15, "isRadiant": false, "win": 1, "lose": 0, "total_gold": 11859, "total_xp": 15292, "kills_per_min": 0.02824858757062147, "kda": 2, "abandons": 0, "rank_tier": null, "cosmetics": [], "benchmarks": {"gold_per_min": {"raw": 335, "pct": 0.5427789185489391}, "xp_per_min": {"raw": 432, "pct": 0.41683778234086244}, "kills_per_min": {"raw": 0.02824858757062147, "pct": 0.13210130047912388}, "last_hits_per_min": {"raw": 1.2994350282485876, "pct": 0.324435318275154}, "hero_damage_per_min": {"raw": 160.22598870056495, "pct": 0.06023271731690623}, "hero_healing_per_min": {"raw": 0, "pct": 0.5017111567419575}, "tower_damage": {"raw": 3971, "pct": 0.6789869952087612}, "stuns_per_min": {"raw": 0, "pct": 0}, "lhten": {}}}, {"match_id": 6514176015, "player_slot": 129, "ability_targets": null, "ability_upgrades_arr": [5098, 5100, 5099, 5099, 5099, 5101, 5098, 5100, 5098, 5099, 5100, 5101, 6926, 5100, 5903, 5098, 5101, 762], "ability_uses": null, "account_id": 127693554, "actions": null, "additional_units": null, "assists": 14, "backpack_0": 0, "backpack_1": 0, "backpack_2": 0, "backpack_3": null, "buyback_log": null, "camps_stacked": null, "connection_log": null, "creeps_stacked": null, "damage": null, "damage_inflictor": null, "damage_inflictor_received": null, "damage_taken": null, "damage_targets": null, "deaths": 5, "denies": 6, "dn_t": null, "firstblood_claimed": null, "gold": 2525, "gold_per_min": 478, "gold_reasons": null, "gold_spent": 13395, "gold_t": null, "hero_damage": 14531, "hero_healing": 0, "hero_hits": null, "hero_id": 17, "item_0": 116, "item_1": 63, "item_2": 98, "item_3": 259, "item_4": 77, "item_5": 77, "item_neutral": 287, "item_uses": null, "kill_streaks": null, "killed": null, "killed_by": null, "kills": 5, "kills_log": null, "lane_pos": null, "last_hits": 167, "leaver_status": 0, "level": 23, "lh_t": null, "life_state": null, "max_hero_hit": null, "multi_kills": null, "net_worth": 14510, "obs": null, "obs_left_log": null, "obs_log": null, "obs_placed": null, "party_id": 6, "party_size": 1, "performance_others": null, "permanent_buffs": [{"permanent_buff": 6, "stack_count": 2}], "pings": null, "pred_vict": null, "purchase": null, "purchase_log": null, "randomed": null, "repicked": null, "roshans_killed": null, "rune_pickups": null, "runes": null, "runes_log": null, "sen": null, "sen_left_log": null, "sen_log": null, "sen_placed": null, "stuns": null, "teamfight_participation": null, "times": null, "tower_damage": 3749, "towers_killed": null, "xp_per_min": 701, "xp_reasons": null, "xp_t": null, "personaname": "[FYWL] Galleta soda say:", "name": null, "last_login": null, "radiant_win": false, "start_time": 1649388055, "duration": 2124, "cluster": 251, "lobby_type": 7, "game_mode": 22, "is_contributor": false, "patch": 50, "region": 15, "isRadiant": false, "win": 1, "lose": 0, "total_gold": 16921, "total_xp": 24815, "kills_per_min": 0.14124293785310735, "kda": 3, "abandons": 0, "rank_tier": 22, "cosmetics": [], "benchmarks": {"gold_per_min": {"raw": 478, "pct": 0.35068691250903833}, "xp_per_min": {"raw": 701, "pct": 0.467823571945047}, "kills_per_min": {"raw": 0.14124293785310735, "pct": 0.14316702819956617}, "last_hits_per_min": {"raw": 4.7175141242937855, "pct": 0.24222704266088213}, "hero_damage_per_min": {"raw": 410.48022598870057, "pct": 0.10267534345625452}, "hero_healing_per_min": {"raw": 0, "pct": 0.8481561822125814}, "tower_damage": {"raw": 3749, "pct": 0.779464931308749}, "stuns_per_min": {"raw": 0, "pct": 0.0014461315979754157}, "lhten": {}}}, {"match_id": 6514176015, "player_slot": 130, "ability_targets": null, "ability_upgrades_arr": [5154, 5155, 5154, 5156, 5154, 5157, 5154, 5156, 5155, 5938, 5156, 5157, 5156, 5155, 5907, 5155, 5157, 6896, 5943], "ability_uses": null, "account_id": null, "actions": null, "additional_units": null, "assists": 12, "backpack_0": 36, "backpack_1": 0, "backpack_2": 0, "backpack_3": null, "buyback_log": null, "camps_stacked": null, "connection_log": null, "creeps_stacked": null, "damage": null, "damage_inflictor": null, "damage_inflictor_received": null, "damage_taken": null, "damage_targets": null, "deaths": 0, "denies": 7, "dn_t": null, "firstblood_claimed": null, "gold": 2457, "gold_per_min": 702, "gold_reasons": null, "gold_spent": 25305, "gold_t": null, "hero_damage": 41675, "hero_healing": 0, "hero_hits": null, "hero_id": 35, "item_0": 166, "item_1": 160, "item_2": 236, "item_3": 139, "item_4": 63, "item_5": 249, "item_neutral": 381, "item_uses": null, "kill_streaks": null, "killed": null, "killed_by": null, "kills": 15, "kills_log": null, "lane_pos": null, "last_hits": 282, "leaver_status": 0, "level": 25, "lh_t": null, "life_state": null, "max_hero_hit": null, "multi_kills": null, "net_worth": 24732, "obs": null, "obs_left_log": null, "obs_log": null, "obs_placed": null, "party_id": 7, "party_size": 1, "performance_others": null, "permanent_buffs": [], "pings": null, "pred_vict": null, "purchase": null, "purchase_log": null, "randomed": null, "repicked": null, "roshans_killed": null, "rune_pickups": null, "runes": null, "runes_log": null, "sen": null, "sen_left_log": null, "sen_log": null, "sen_placed": null, "stuns": null, "teamfight_participation": null, "times": null, "tower_damage": 20552, "towers_killed": null, "xp_per_min": 809, "xp_reasons": null, "xp_t": null, "radiant_win": false, "start_time": 1649388055, "duration": 2124, "cluster": 251, "lobby_type": 7, "game_mode": 22, "is_contributor": false, "patch": 50, "region": 15, "isRadiant": false, "win": 1, "lose": 0, "total_gold": 24850, "total_xp": 28638, "kills_per_min": 0.42372881355932207, "kda": 27, "abandons": 0, "rank_tier": null, "cosmetics": [], "benchmarks": {"gold_per_min": {"raw": 702, "pct": 0.8815575987020011}, "xp_per_min": {"raw": 809, "pct": 0.8469442942130881}, "kills_per_min": {"raw": 0.423728813559322, "pct": 0.8696592752839373}, "last_hits_per_min": {"raw": 7.966101694915254, "pct": 0.7934018388318009}, "hero_damage_per_min": {"raw": 1177.2598870056497, "pct": 0.8447809626825311}, "hero_healing_per_min": {"raw": 0, "pct": 0.9351000540832882}, "tower_damage": {"raw": 20552, "pct": 0.9832341806381828}, "stuns_per_min": {"raw": 0, "pct": 0.04921579232017307}, "lhten": {}}}, {"match_id": 6514176015, "player_slot": 131, "ability_targets": null, "ability_upgrades_arr": [5044, 5046, 5044, 5046, 5045, 5047, 5044, 5044, 5046, 5046, 6366, 5047, 5045, 5045, 781, 5045, 5047, 541], "ability_uses": null, "account_id": null, "actions": null, "additional_units": null, "assists": 12, "backpack_0": 0, "backpack_1": 0, "backpack_2": 0, "backpack_3": null, "buyback_log": null, "camps_stacked": null, "connection_log": null, "creeps_stacked": null, "damage": null, "damage_inflictor": null, "damage_inflictor_received": null, "damage_taken": null, "damage_targets": null, "deaths": 8, "denies": 1, "dn_t": null, "firstblood_claimed": null, "gold": 1043, "gold_per_min": 338, "gold_reasons": null, "gold_spent": 10590, "gold_t": null, "hero_damage": 11425, "hero_healing": 306, "hero_hits": null, "hero_id": 26, "item_0": 1, "item_1": 108, "item_2": 94, "item_3": 214, "item_4": 232, "item_5": 0, "item_neutral": 289, "item_uses": null, "kill_streaks": null, "killed": null, "killed_by": null, "kills": 8, "kills_log": null, "lane_pos": null, "last_hits": 30, "leaver_status": 0, "level": 20, "lh_t": null, "life_state": null, "max_hero_hit": null, "multi_kills": null, "net_worth": 11118, "obs": null, "obs_left_log": null, "obs_log": null, "obs_placed": null, "party_id": 8, "party_size": 1, "performance_others": null, "permanent_buffs": [{"permanent_buff": 6, "stack_count": 1}, {"permanent_buff": 7, "stack_count": 5}], "pings": null, "pred_vict": null, "purchase": null, "purchase_log": null, "randomed": null, "repicked": null, "roshans_killed": null, "rune_pickups": null, "runes": null, "runes_log": null, "sen": null, "sen_left_log": null, "sen_log": null, "sen_placed": null, "stuns": null, "teamfight_participation": null, "times": null, "tower_damage": 1383, "towers_killed": null, "xp_per_min": 520, "xp_reasons": null, "xp_t": null, "radiant_win": false, "start_time": 1649388055, "duration": 2124, "cluster": 251, "lobby_type": 7, "game_mode": 22, "is_contributor": false, "patch": 50, "region": 15, "isRadiant": false, "win": 1, "lose": 0, "total_gold": 11965, "total_xp": 18408, "kills_per_min": 0.22598870056497175, "kda": 2, "abandons": 0, "rank_tier": null, "cosmetics": [], "benchmarks": {"gold_per_min": {"raw": 338, "pct": 0.6965302951838426}, "xp_per_min": {"raw": 520, "pct": 0.5903676851372346}, "kills_per_min": {"raw": 0.22598870056497175, "pct": 0.8544795442775763}, "last_hits_per_min": {"raw": 0.847457627118644, "pct": 0.3832211289487312}, "hero_damage_per_min": {"raw": 322.7401129943503, "pct": 0.6126359399274987}, "hero_healing_per_min": {"raw": 8.64406779661017, "pct": 0.7146556188503366}, "tower_damage": {"raw": 1383, "pct": 0.8632832729155878}, "stuns_per_min": {"raw": 0, "pct": 0}, "lhten": {}}}, {"match_id": 6514176015, "player_slot": 132, "ability_targets": null, "ability_upgrades_arr": [5359, 5357, 5358, 5357, 5359, 5360, 5359, 5359, 5358, 5358, 6975, 5360, 5357, 5358, 6195, 5357, 5360, 758, 6973], "ability_uses": null, "account_id": null, "actions": null, "additional_units": null, "assists": 14, "backpack_0": 0, "backpack_1": 569, "backpack_2": 0, "backpack_3": null, "buyback_log": null, "camps_stacked": null, "connection_log": null, "creeps_stacked": null, "damage": null, "damage_inflictor": null, "damage_inflictor_received": null, "damage_taken": null, "damage_targets": null, "deaths": 4, "denies": 7, "dn_t": null, "firstblood_claimed": null, "gold": 2776, "gold_per_min": 686, "gold_reasons": null, "gold_spent": 21780, "gold_t": null, "hero_damage": 32513, "hero_healing": 0, "hero_hits": null, "hero_id": 70, "item_0": 160, "item_1": 36, "item_2": 154, "item_3": 50, "item_4": 145, "item_5": 116, "item_neutral": 376, "item_uses": null, "kill_streaks": null, "killed": null, "killed_by": null, "kills": 9, "kills_log": null, "lane_pos": null, "last_hits": 308, "leaver_status": 0, "level": 26, "lh_t": null, "life_state": null, "max_hero_hit": null, "multi_kills": null, "net_worth": 24701, "obs": null, "obs_left_log": null, "obs_log": null, "obs_placed": null, "party_id": 9, "party_size": 1, "performance_others": null, "permanent_buffs": [{"permanent_buff": 12, "stack_count": 0}], "pings": null, "pred_vict": null, "purchase": null, "purchase_log": null, "randomed": null, "repicked": null, "roshans_killed": null, "rune_pickups": null, "runes": null, "runes_log": null, "sen": null, "sen_left_log": null, "sen_log": null, "sen_placed": null, "stuns": null, "teamfight_participation": null, "times": null, "tower_damage": 6109, "towers_killed": null, "xp_per_min": 848, "xp_reasons": null, "xp_t": null, "radiant_win": false, "start_time": 1649388055, "duration": 2124, "cluster": 251, "lobby_type": 7, "game_mode": 22, "is_contributor": false, "patch": 50, "region": 15, "isRadiant": false, "win": 1, "lose": 0, "total_gold": 24284, "total_xp": 30019, "kills_per_min": 0.2542372881355932, "kda": 4, "abandons": 0, "rank_tier": null, "cosmetics": [], "benchmarks": {"gold_per_min": {"raw": 686, "pct": 0.8810872027180068}, "xp_per_min": {"raw": 848, "pct": 0.8573046432616082}, "kills_per_min": {"raw": 0.2542372881355932, "pct": 0.42129105322763305}, "last_hits_per_min": {"raw": 8.700564971751412, "pct": 0.9411098527746319}, "hero_damage_per_min": {"raw": 918.4463276836159, "pct": 0.7180067950169875}, "hero_healing_per_min": {"raw": 0, "pct": 0.9694224235560589}, "tower_damage": {"raw": 6109, "pct": 0.711211778029445}, "stuns_per_min": {"raw": 0, "pct": 0.25934314835787087}, "lhten": {}}}], "patch": 50, "region": 15, "replay_url": "http://replay251.valve.net/570/6514176015_1168160766.dem.bz2"}