{"match_id": 6514169966, "barracks_status_dire": 63, "barracks_status_radiant": 0, "chat": null, "cluster": 202, "cosmetics": null, "dire_score": 59, "dire_team_id": null, "draft_timings": null, "duration": 2515, "engine": 1, "first_blood_time": 9, "game_mode": 22, "human_players": 10, "leagueid": 0, "lobby_type": 7, "match_seq_num": 5441612480, "negative_votes": 0, "objectives": null, "picks_bans": [{"is_pick": true, "hero_id": 28, "team": 1, "order": 0}, {"is_pick": true, "hero_id": 27, "team": 0, "order": 1}, {"is_pick": true, "hero_id": 75, "team": 0, "order": 2}, {"is_pick": true, "hero_id": 87, "team": 1, "order": 3}, {"is_pick": true, "hero_id": 21, "team": 0, "order": 4}, {"is_pick": true, "hero_id": 40, "team": 1, "order": 5}, {"is_pick": true, "hero_id": 76, "team": 0, "order": 6}, {"is_pick": true, "hero_id": 110, "team": 1, "order": 7}, {"is_pick": true, "hero_id": 70, "team": 1, "order": 8}, {"is_pick": true, "hero_id": 113, "team": 0, "order": 9}, {"is_pick": false, "hero_id": 81, "team": 0, "order": 10}, {"is_pick": false, "hero_id": 39, "team": 0, "order": 11}, {"is_pick": false, "hero_id": 105, "team": 0, "order": 12}, {"is_pick": false, "hero_id": 101, "team": 0, "order": 13}, {"is_pick": false, "hero_id": 75, "team": 0, "order": 14}], "positive_votes": 0, "radiant_gold_adv": null, "radiant_score": 40, "radiant_team_id": null, "radiant_win": false, "radiant_xp_adv": null, "skill": null, "start_time": 1649387496, "teamfights": null, "tower_status_dire": 2038, "tower_status_radiant": 0, "version": null, "replay_salt": 630476652, "series_id": 0, "series_type": 0, "players": [{"match_id": 6514169966, "player_slot": 0, "ability_targets": null, "ability_upgrades_arr": [5080, 5079, 5080, 5079, 5080, 5081, 5080, 5079, 5079, 468, 5078, 5081, 5078, 793, 5078, 5078, 5081, 760], "ability_uses": null, "account_id": null, "actions": null, "additional_units": null, "assists": 15, "backpack_0": 0, "backpack_1": 0, "backpack_2": 0, "backpack_3": null, "buyback_log": null, "camps_stacked": null, "connection_log": null, "creeps_stacked": null, "damage": null, "damage_inflictor": null, "damage_inflictor_received": null, "damage_taken": null, "damage_targets": null, "deaths": 12, "denies": 5, "dn_t": null, "firstblood_claimed": null, "gold": 1486, "gold_per_min": 407, "gold_reasons": null, "gold_spent": 13905, "gold_t": null, "hero_damage": 24893, "hero_healing": 0, "hero_hits": null, "hero_id": 27, "item_0": 36, "item_1": 108, "item_2": 265, "item_3": 254, "item_4": 214, "item_5": 232, "item_neutral": 289, "item_uses": null, "kill_streaks": null, "killed": null, "killed_by": null, "kills": 5, "kills_log": null, "lane_pos": null, "last_hits": 155, "leaver_status": 0, "level": 22, "lh_t": null, "life_state": null, "max_hero_hit": null, "multi_kills": null, "net_worth": 13011, "obs": null, "obs_left_log": null, "obs_log": null, "obs_placed": null, "party_id": 0, "party_size": 1, "performance_others": null, "permanent_buffs": [{"permanent_buff": 6, "stack_count": 1}, {"permanent_buff": 12, "stack_count": 0}], "pings": null, "pred_vict": null, "purchase": null, "purchase_log": null, "randomed": null, "repicked": null, "roshans_killed": null, "rune_pickups": null, "runes": null, "runes_log": null, "sen": null, "sen_left_log": null, "sen_log": null, "sen_placed": null, "stuns": null, "teamfight_participation": null, "times": null, "tower_damage": 143, "towers_killed": null, "xp_per_min": 529, "xp_reasons": null, "xp_t": null, "radiant_win": false, "start_time": 1649387496, "duration": 2515, "cluster": 202, "lobby_type": 7, "game_mode": 22, "is_contributor": false, "patch": 50, "region": 10, "isRadiant": true, "win": 0, "lose": 1, "total_gold": 17060, "total_xp": 22173, "kills_per_min": 0.11928429423459246, "kda": 1, "abandons": 0, "rank_tier": null, "cosmetics": [], "benchmarks": {"gold_per_min": {"raw": 407, "pct": 0.836413415468857}, "xp_per_min": {"raw": 529, "pct": 0.6783025325119781}, "kills_per_min": {"raw": 0.11928429423459243, "pct": 0.6872005475701575}, "last_hits_per_min": {"raw": 3.697813121272366, "pct": 0.919233401779603}, "hero_damage_per_min": {"raw": 593.8687872763419, "pct": 0.9247091033538672}, "hero_healing_per_min": {"raw": 0, "pct": 0.5017111567419575}, "tower_damage": {"raw": 143, "pct": 0.17248459958932238}, "stuns_per_min": {"raw": 0, "pct": 0}, "lhten": {}}}, {"match_id": 6514169966, "player_slot": 1, "ability_targets": null, "ability_upgrades_arr": [5392, 5391, 5684, 5392, 5392, 5394, 5392, 5391, 5391, 5391, 5394, 5906, 5684, 5684, 5684, 6141, 5394, 7375, 6241], "ability_uses": null, "account_id": 123129223, "actions": null, "additional_units": null, "assists": 5, "backpack_0": 0, "backpack_1": 0, "backpack_2": 0, "backpack_3": null, "buyback_log": null, "camps_stacked": null, "connection_log": null, "creeps_stacked": null, "damage": null, "damage_inflictor": null, "damage_inflictor_received": null, "damage_taken": null, "damage_targets": null, "deaths": 11, "denies": 11, "dn_t": null, "firstblood_claimed": null, "gold": 3702, "gold_per_min": 434, "gold_reasons": null, "gold_spent": 11125, "gold_t": null, "hero_damage": 36195, "hero_healing": 0, "hero_hits": null, "hero_id": 76, "item_0": 63, "item_1": 1, "item_2": 223, "item_3": 116, "item_4": 0, "item_5": 0, "item_neutral": 361, "item_uses": null, "kill_streaks": null, "killed": null, "killed_by": null, "kills": 19, "kills_log": null, "lane_pos": null, "last_hits": 117, "leaver_status": 0, "level": 25, "lh_t": null, "life_state": null, "max_hero_hit": null, "multi_kills": null, "net_worth": 14052, "obs": null, "obs_left_log": null, "obs_log": null, "obs_placed": null, "party_id": 1, "party_size": 1, "performance_others": null, "permanent_buffs": [], "pings": null, "pred_vict": null, "purchase": null, "purchase_log": null, "randomed": null, "repicked": null, "roshans_killed": null, "rune_pickups": null, "runes": null, "runes_log": null, "sen": null, "sen_left_log": null, "sen_log": null, "sen_placed": null, "stuns": null, "teamfight_participation": null, "times": null, "tower_damage": 870, "towers_killed": null, "xp_per_min": 685, "xp_reasons": null, "xp_t": null, "personaname": "oSavedra", "name": null, "last_login": "2018-02-24T06:29:58.140Z", "radiant_win": false, "start_time": 1649387496, "duration": 2515, "cluster": 202, "lobby_type": 7, "game_mode": 22, "is_contributor": false, "patch": 50, "region": 10, "isRadiant": true, "win": 0, "lose": 1, "total_gold": 18191, "total_xp": 28712, "kills_per_min": 0.4532803180914513, "kda": 2, "abandons": 0, "rank_tier": 42, "cosmetics": [], "benchmarks": {"gold_per_min": {"raw": 434, "pct": 0.31198686371100165}, "xp_per_min": {"raw": 685, "pct": 0.535303776683087}, "kills_per_min": {"raw": 0.45328031809145125, "pct": 0.8637110016420362}, "last_hits_per_min": {"raw": 2.7912524850894633, "pct": 0.12151067323481117}, "hero_damage_per_min": {"raw": 863.4990059642147, "pct": 0.6403940886699507}, "hero_healing_per_min": {"raw": 0, "pct": 0.9589490968801314}, "tower_damage": {"raw": 870, "pct": 0.22495894909688013}, "stuns_per_min": {"raw": 0, "pct": 0}, "lhten": {}}}, {"match_id": 6514169966, "player_slot": 2, "ability_targets": null, "ability_upgrades_arr": [5377, 5379, 5379, 5377, 5378, 5380, 5377, 5377, 5379, 6184, 5379, 5380, 5378, 5378, 410, 5378, 5380, 6880], "ability_uses": null, "account_id": 38334589, "actions": null, "additional_units": null, "assists": 12, "backpack_0": 0, "backpack_1": 0, "backpack_2": 0, "backpack_3": null, "buyback_log": null, "camps_stacked": null, "connection_log": null, "creeps_stacked": null, "damage": null, "damage_inflictor": null, "damage_inflictor_received": null, "damage_taken": null, "damage_targets": null, "deaths": 13, "denies": 10, "dn_t": null, "firstblood_claimed": null, "gold": 687, "gold_per_min": 376, "gold_reasons": null, "gold_spent": 14240, "gold_t": null, "hero_damage": 25575, "hero_healing": 0, "hero_hits": null, "hero_id": 75, "item_0": 36, "item_1": 534, "item_2": 116, "item_3": 77, "item_4": 63, "item_5": 263, "item_neutral": 573, "item_uses": null, "kill_streaks": null, "killed": null, "killed_by": null, "kills": 6, "kills_log": null, "lane_pos": null, "last_hits": 107, "leaver_status": 0, "level": 22, "lh_t": null, "life_state": null, "max_hero_hit": null, "multi_kills": null, "net_worth": 14142, "obs": null, "obs_left_log": null, "obs_log": null, "obs_placed": null, "party_id": 2, "party_size": 1, "performance_others": null, "permanent_buffs": [{"permanent_buff": 3, "stack_count": 30}, {"permanent_buff": 6, "stack_count": 1}], "pings": null, "pred_vict": null, "purchase": null, "purchase_log": null, "randomed": null, "repicked": null, "roshans_killed": null, "rune_pickups": null, "runes": null, "runes_log": null, "sen": null, "sen_left_log": null, "sen_log": null, "sen_placed": null, "stuns": null, "teamfight_participation": null, "times": null, "tower_damage": 100, "towers_killed": null, "xp_per_min": 549, "xp_reasons": null, "xp_t": null, "personaname": "kingcba", "name": null, "last_login": null, "radiant_win": false, "start_time": 1649387496, "duration": 2515, "cluster": 202, "lobby_type": 7, "game_mode": 22, "is_contributor": false, "patch": 50, "region": 10, "isRadiant": true, "win": 0, "lose": 1, "total_gold": 15760, "total_xp": 23012, "kills_per_min": 0.14314115308151093, "kda": 1, "abandons": 0, "rank_tier": 41, "cosmetics": [], "benchmarks": {"gold_per_min": {"raw": 376, "pct": 0.49176954732510286}, "xp_per_min": {"raw": 549, "pct": 0.4787379972565158}, "kills_per_min": {"raw": 0.14314115308151096, "pct": 0.39574759945130317}, "last_hits_per_min": {"raw": 2.552683896620278, "pct": 0.5020576131687243}, "hero_damage_per_min": {"raw": 610.1391650099404, "pct": 0.5432098765432098}, "hero_healing_per_min": {"raw": 0, "pct": 0.7558299039780522}, "tower_damage": {"raw": 100, "pct": 0.23731138545953362}, "stuns_per_min": {"raw": 0, "pct": 0.8525377229080933}, "lhten": {}}}, {"match_id": 6514169966, "player_slot": 3, "ability_targets": null, "ability_upgrades_arr": [5679, 5677, 5679, 5677, 5679, 5683, 5678, 5679, 5678, 5677, 6405, 5683, 5678, 5677, 5678, 7104, 5683, 6287, 685], "ability_uses": null, "account_id": null, "actions": null, "additional_units": [{"unitname": "", "item_0": 166, "item_1": 65, "item_2": 263, "item_3": 116, "item_4": 249, "item_5": 48, "backpack_0": 0, "backpack_1": 0, "backpack_2": 0, "item_neutral": 0}], "assists": 6, "backpack_0": 0, "backpack_1": 0, "backpack_2": 0, "backpack_3": null, "buyback_log": null, "camps_stacked": null, "connection_log": null, "creeps_stacked": null, "damage": null, "damage_inflictor": null, "damage_inflictor_received": null, "damage_taken": null, "damage_targets": null, "deaths": 11, "denies": 9, "dn_t": null, "firstblood_claimed": null, "gold": 1807, "gold_per_min": 631, "gold_reasons": null, "gold_spent": 23860, "gold_t": null, "hero_damage": 28182, "hero_healing": 0, "hero_hits": null, "hero_id": 113, "item_0": 166, "item_1": 65, "item_2": 263, "item_3": 116, "item_4": 249, "item_5": 48, "item_neutral": 686, "item_uses": null, "kill_streaks": null, "killed": null, "killed_by": null, "kills": 6, "kills_log": null, "lane_pos": null, "last_hits": 320, "leaver_status": 0, "level": 25, "lh_t": null, "life_state": null, "max_hero_hit": null, "multi_kills": null, "net_worth": 23157, "obs": null, "obs_left_log": null, "obs_log": null, "obs_placed": null, "party_id": 3, "party_size": 1, "performance_others": null, "permanent_buffs": [], "pings": null, "pred_vict": null, "purchase": null, "purchase_log": null, "randomed": null, "repicked": null, "roshans_killed": null, "rune_pickups": null, "runes": null, "runes_log": null, "sen": null, "sen_left_log": null, "sen_log": null, "sen_placed": null, "stuns": null, "teamfight_participation": null, "times": null, "tower_damage": 683, "towers_killed": null, "xp_per_min": 729, "xp_reasons": null, "xp_t": null, "radiant_win": false, "start_time": 1649387496, "duration": 2515, "cluster": 202, "lobby_type": 7, "game_mode": 22, "is_contributor": false, "patch": 50, "region": 10, "isRadiant": true, "win": 0, "lose": 1, "total_gold": 26449, "total_xp": 30557, "kills_per_min": 0.14314115308151093, "kda": 1, "abandons": 0, "rank_tier": null, "cosmetics": [], "benchmarks": {"gold_per_min": {"raw": 631, "pct": 0.4394904458598726}, "xp_per_min": {"raw": 729, "pct": 0.4989384288747346}, "kills_per_min": {"raw": 0.14314115308151096, "pct": 0.267515923566879}, "last_hits_per_min": {"raw": 7.634194831013915, "pct": 0.5774946921443737}, "hero_damage_per_min": {"raw": 672.3339960238568, "pct": 0.2484076433121019}, "hero_healing_per_min": {"raw": 0, "pct": 0.9617834394904459}, "tower_damage": {"raw": 683, "pct": 0.24203821656050956}, "stuns_per_min": {"raw": 0, "pct": 0.5392781316348195}, "lhten": {}}}, {"match_id": 6514169966, "player_slot": 4, "ability_targets": null, "ability_upgrades_arr": [5130, 5132, 5130, 5131, 5131, 5131, 5133, 5131, 5132, 7890, 5132, 5133, 5132, 5130, 6992, 5130, 5133, 7062], "ability_uses": null, "account_id": null, "actions": null, "additional_units": null, "assists": 13, "backpack_0": 0, "backpack_1": 0, "backpack_2": 0, "backpack_3": null, "buyback_log": null, "camps_stacked": null, "connection_log": null, "creeps_stacked": null, "damage": null, "damage_inflictor": null, "damage_inflictor_received": null, "damage_taken": null, "damage_targets": null, "deaths": 12, "denies": 6, "dn_t": null, "firstblood_claimed": null, "gold": 225, "gold_per_min": 281, "gold_reasons": null, "gold_spent": 9785, "gold_t": null, "hero_damage": 9549, "hero_healing": 69, "hero_hits": null, "hero_id": 21, "item_0": 90, "item_1": 34, "item_2": 98, "item_3": 0, "item_4": 29, "item_5": 43, "item_neutral": 326, "item_uses": null, "kill_streaks": null, "killed": null, "killed_by": null, "kills": 1, "kills_log": null, "lane_pos": null, "last_hits": 59, "leaver_status": 0, "level": 21, "lh_t": null, "life_state": null, "max_hero_hit": null, "multi_kills": null, "net_worth": 8025, "obs": null, "obs_left_log": null, "obs_log": null, "obs_placed": null, "party_id": 4, "party_size": 1, "performance_others": null, "permanent_buffs": [{"permanent_buff": 6, "stack_count": 1}], "pings": null, "pred_vict": null, "purchase": null, "purchase_log": null, "randomed": null, "repicked": null, "roshans_killed": null, "rune_pickups": null, "runes": null, "runes_log": null, "sen": null, "sen_left_log": null, "sen_log": null, "sen_placed": null, "stuns": null, "teamfight_participation": null, "times": null, "tower_damage": 0, "towers_killed": null, "xp_per_min": 508, "xp_reasons": null, "xp_t": null, "radiant_win": false, "start_time": 1649387496, "duration": 2515, "cluster": 202, "lobby_type": 7, "game_mode": 22, "is_contributor": false, "patch": 50, "region": 10, "isRadiant": true, "win": 0, "lose": 1, "total_gold": 11778, "total_xp": 21293, "kills_per_min": 0.023856858846918492, "kda": 1, "abandons": 0, "rank_tier": null, "cosmetics": [], "benchmarks": {"gold_per_min": {"raw": 281, "pct": 0.08816120906801007}, "xp_per_min": {"raw": 508, "pct": 0.28295549958018473}, "kills_per_min": {"raw": 0.02385685884691849, "pct": 0.03526448362720403}, "last_hits_per_min": {"raw": 1.4075546719681908, "pct": 0.09655751469353484}, "hero_damage_per_min": {"raw": 227.80914512922465, "pct": 0.02686817800167926}, "hero_healing_per_min": {"raw": 1.6461232604373757, "pct": 0.8287153652392947}, "tower_damage": {"raw": 0, "pct": 0.10579345088161209}, "stuns_per_min": {"raw": 0, "pct": 0.0025188916876574307}, "lhten": {}}}, {"match_id": 6514169966, "player_slot": 128, "ability_targets": null, "ability_upgrades_arr": [5116, 5114, 5115, 5116, 5116, 5117, 5116, 5115, 5115, 5115, 5114, 5117, 852, 5114, 6423, 5114, 5117, 6211], "ability_uses": null, "account_id": null, "actions": null, "additional_units": null, "assists": 19, "backpack_0": 16, "backpack_1": 0, "backpack_2": 0, "backpack_3": null, "buyback_log": null, "camps_stacked": null, "connection_log": null, "creeps_stacked": null, "damage": null, "damage_inflictor": null, "damage_inflictor_received": null, "damage_taken": null, "damage_targets": null, "deaths": 5, "denies": 11, "dn_t": null, "firstblood_claimed": null, "gold": 4334, "gold_per_min": 486, "gold_reasons": null, "gold_spent": 16250, "gold_t": null, "hero_damage": 14960, "hero_healing": 0, "hero_hits": null, "hero_id": 28, "item_0": 63, "item_1": 34, "item_2": 90, "item_3": 226, "item_4": 1, "item_5": 53, "item_neutral": 573, "item_uses": null, "kill_streaks": null, "killed": null, "killed_by": null, "kills": 8, "kills_log": null, "lane_pos": null, "last_hits": 193, "leaver_status": 0, "level": 26, "lh_t": null, "life_state": null, "max_hero_hit": null, "multi_kills": null, "net_worth": 19959, "obs": null, "obs_left_log": null, "obs_log": null, "obs_placed": null, "party_id": 5, "party_size": 1, "performance_others": null, "permanent_buffs": [{"permanent_buff": 12, "stack_count": 0}], "pings": null, "pred_vict": null, "purchase": null, "purchase_log": null, "randomed": null, "repicked": null, "roshans_killed": null, "rune_pickups": null, "runes": null, "runes_log": null, "sen": null, "sen_left_log": null, "sen_log": null, "sen_placed": null, "stuns": null, "teamfight_participation": null, "times": null, "tower_damage": 4905, "towers_killed": null, "xp_per_min": 701, "xp_reasons": null, "xp_t": null, "radiant_win": false, "start_time": 1649387496, "duration": 2515, "cluster": 202, "lobby_type": 7, "game_mode": 22, "is_contributor": false, "patch": 50, "region": 10, "isRadiant": false, "win": 1, "lose": 0, "total_gold": 20371, "total_xp": 29383, "kills_per_min": 0.19085487077534793, "kda": 4, "abandons": 0, "rank_tier": null, "cosmetics": [], "benchmarks": {"gold_per_min": {"raw": 486, "pct": 0.7444029850746269}, "xp_per_min": {"raw": 701, "pct": 0.75}, "kills_per_min": {"raw": 0.1908548707753479, "pct": 0.6417910447761194}, "last_hits_per_min": {"raw": 4.604373757455269, "pct": 0.707089552238806}, "hero_damage_per_min": {"raw": 356.89860834990054, "pct": 0.38619402985074625}, "hero_healing_per_min": {"raw": 0, "pct": 0.9552238805970149}, "tower_damage": {"raw": 4905, "pct": 0.9011194029850746}, "stuns_per_min": {"raw": 0, "pct": 0}, "lhten": {}}}, {"match_id": 6514169966, "player_slot": 129, "ability_targets": null, "ability_upgrades_arr": [5179, 5178, 5179, 5178, 5180, 5181, 5180, 5180, 5180, 6979, 5179, 5181, 5179, 5178, 6532, 5178, 5181, 6980], "ability_uses": null, "account_id": null, "actions": null, "additional_units": null, "assists": 17, "backpack_0": 0, "backpack_1": 0, "backpack_2": 0, "backpack_3": null, "buyback_log": null, "camps_stacked": null, "connection_log": null, "creeps_stacked": null, "damage": null, "damage_inflictor": null, "damage_inflictor_received": null, "damage_taken": null, "damage_targets": null, "deaths": 10, "denies": 2, "dn_t": null, "firstblood_claimed": null, "gold": 726, "gold_per_min": 371, "gold_reasons": null, "gold_spent": 15660, "gold_t": null, "hero_damage": 32866, "hero_healing": 1260, "hero_hits": null, "hero_id": 40, "item_0": 48, "item_1": 1, "item_2": 108, "item_3": 244, "item_4": 267, "item_5": 0, "item_neutral": 675, "item_uses": null, "kill_streaks": null, "killed": null, "killed_by": null, "kills": 4, "kills_log": null, "lane_pos": null, "last_hits": 86, "leaver_status": 0, "level": 20, "lh_t": null, "life_state": null, "max_hero_hit": null, "multi_kills": null, "net_worth": 14166, "obs": null, "obs_left_log": null, "obs_log": null, "obs_placed": null, "party_id": 6, "party_size": 1, "performance_others": null, "permanent_buffs": [{"permanent_buff": 6, "stack_count": 2}, {"permanent_buff": 12, "stack_count": 0}], "pings": null, "pred_vict": null, "purchase": null, "purchase_log": null, "randomed": null, "repicked": null, "roshans_killed": null, "rune_pickups": null, "runes": null, "runes_log": null, "sen": null, "sen_left_log": null, "sen_log": null, "sen_placed": null, "stuns": null, "teamfight_participation": null, "times": null, "tower_damage": 1508, "towers_killed": null, "xp_per_min": 444, "xp_reasons": null, "xp_t": null, "radiant_win": false, "start_time": 1649387496, "duration": 2515, "cluster": 202, "lobby_type": 7, "game_mode": 22, "is_contributor": false, "patch": 50, "region": 10, "isRadiant": false, "win": 1, "lose": 0, "total_gold": 15551, "total_xp": 18611, "kills_per_min": 0.09542743538767397, "kda": 1, "abandons": 0, "rank_tier": null, "cosmetics": [], "benchmarks": {"gold_per_min": {"raw": 371, "pct": 0.4988038277511962}, "xp_per_min": {"raw": 444, "pct": 0.3349282296650718}, "kills_per_min": {"raw": 0.09542743538767395, "pct": 0.3708133971291866}, "last_hits_per_min": {"raw": 2.05168986083499, "pct": 0.34330143540669855}, "hero_damage_per_min": {"raw": 784.0795228628231, "pct": 0.5023923444976076}, "hero_healing_per_min": {"raw": 30.059642147117295, "pct": 0.9234449760765551}, "tower_damage": {"raw": 1508, "pct": 0.6148325358851675}, "stuns_per_min": {"raw": 0, "pct": 0.8492822966507177}, "lhten": {}}}, {"match_id": 6514169966, "player_slot": 130, "ability_targets": null, "ability_upgrades_arr": [5359, 5357, 5359, 5358, 5359, 5360, 5359, 5357, 5358, 5358, 5358, 5360, 6975, 5357, 6195, 5357, 5360, 424, 6926, 6029, 758, 6973], "ability_uses": null, "account_id": null, "actions": null, "additional_units": null, "assists": 9, "backpack_0": 0, "backpack_1": 0, "backpack_2": 0, "backpack_3": null, "buyback_log": null, "camps_stacked": null, "connection_log": null, "creeps_stacked": null, "damage": null, "damage_inflictor": null, "damage_inflictor_received": null, "damage_taken": null, "damage_targets": null, "deaths": 5, "denies": 2, "dn_t": null, "firstblood_claimed": null, "gold": 6615, "gold_per_min": 883, "gold_reasons": null, "gold_spent": 30855, "gold_t": null, "hero_damage": 59324, "hero_healing": 0, "hero_hits": null, "hero_id": 70, "item_0": 603, "item_1": 208, "item_2": 156, "item_3": 145, "item_4": 50, "item_5": 108, "item_neutral": 825, "item_uses": null, "kill_streaks": null, "killed": null, "killed_by": null, "kills": 25, "kills_log": null, "lane_pos": null, "last_hits": 419, "leaver_status": 0, "level": 30, "lh_t": null, "life_state": null, "max_hero_hit": null, "multi_kills": null, "net_worth": 35915, "obs": null, "obs_left_log": null, "obs_log": null, "obs_placed": null, "party_id": 7, "party_size": 1, "performance_others": null, "permanent_buffs": [{"permanent_buff": 12, "stack_count": 0}], "pings": null, "pred_vict": null, "purchase": null, "purchase_log": null, "randomed": null, "repicked": null, "roshans_killed": null, "rune_pickups": null, "runes": null, "runes_log": null, "sen": null, "sen_left_log": null, "sen_log": null, "sen_placed": null, "stuns": null, "teamfight_participation": null, "times": null, "tower_damage": 14464, "towers_killed": null, "xp_per_min": 926, "xp_reasons": null, "xp_t": null, "radiant_win": false, "start_time": 1649387496, "duration": 2515, "cluster": 202, "lobby_type": 7, "game_mode": 22, "is_contributor": false, "patch": 50, "region": 10, "isRadiant": false, "win": 1, "lose": 0, "total_gold": 37012, "total_xp": 38814, "kills_per_min": 0.5964214711729623, "kda": 5, "abandons": 0, "rank_tier": null, "cosmetics": [], "benchmarks": {"gold_per_min": {"raw": 883, "pct": 0.9977349943374858}, "xp_per_min": {"raw": 926, "pct": 0.9626274065685164}, "kills_per_min": {"raw": 0.5964214711729623, "pct": 0.9207248018120046}, "last_hits_per_min": {"raw": 9.996023856858846, "pct": 0.9818799546998868}, "hero_damage_per_min": {"raw": 1415.2842942345926, "pct": 0.9648924122310306}, "hero_healing_per_min": {"raw": 0, "pct": 0.9694224235560589}, "tower_damage": {"raw": 14464, "pct": 0.9739524348810872}, "stuns_per_min": {"raw": 0, "pct": 0.25934314835787087}, "lhten": {}}}, {"match_id": 6514169966, "player_slot": 131, "ability_targets": null, "ability_upgrades_arr": [5625, 5623, 5631, 5623, 5625, 5630, 5631, 5623, 5623, 5996, 5626, 5630, 5626, 5626, 6401, 5626, 5630, 6915, 6852, 406, 6235], "ability_uses": null, "account_id": null, "actions": null, "additional_units": null, "assists": 19, "backpack_0": 0, "backpack_1": 0, "backpack_2": 0, "backpack_3": null, "buyback_log": null, "camps_stacked": null, "connection_log": null, "creeps_stacked": null, "damage": null, "damage_inflictor": null, "damage_inflictor_received": null, "damage_taken": null, "damage_targets": null, "deaths": 9, "denies": 8, "dn_t": null, "firstblood_claimed": null, "gold": 1061, "gold_per_min": 591, "gold_reasons": null, "gold_spent": 19930, "gold_t": null, "hero_damage": 56936, "hero_healing": 1043, "hero_hits": null, "hero_id": 110, "item_0": 116, "item_1": 48, "item_2": 0, "item_3": 190, "item_4": 176, "item_5": 110, "item_neutral": 589, "item_uses": null, "kill_streaks": null, "killed": null, "killed_by": null, "kills": 16, "kills_log": null, "lane_pos": null, "last_hits": 194, "leaver_status": 0, "level": 28, "lh_t": null, "life_state": null, "max_hero_hit": null, "multi_kills": null, "net_worth": 20266, "obs": null, "obs_left_log": null, "obs_log": null, "obs_placed": null, "party_id": 8, "party_size": 1, "performance_others": null, "permanent_buffs": [{"permanent_buff": 6, "stack_count": 1}, {"permanent_buff": 12, "stack_count": 0}], "pings": null, "pred_vict": null, "purchase": null, "purchase_log": null, "randomed": null, "repicked": null, "roshans_killed": null, "rune_pickups": null, "runes": null, "runes_log": null, "sen": null, "sen_left_log": null, "sen_log": null, "sen_placed": null, "stuns": null, "teamfight_participation": null, "times": null, "tower_damage": 3626, "towers_killed": null, "xp_per_min": 947, "xp_reasons": null, "xp_t": null, "radiant_win": false, "start_time": 1649387496, "duration": 2515, "cluster": 202, "lobby_type": 7, "game_mode": 22, "is_contributor": false, "patch": 50, "region": 10, "isRadiant": false, "win": 1, "lose": 0, "total_gold": 24772, "total_xp": 39695, "kills_per_min": 0.38170974155069587, "kda": 3, "abandons": 0, "rank_tier": null, "cosmetics": [], "benchmarks": {"gold_per_min": {"raw": 591, "pct": 0.9812646370023419}, "xp_per_min": {"raw": 947, "pct": 0.9976580796252927}, "kills_per_min": {"raw": 0.3817097415506958, "pct": 0.9718969555035128}, "last_hits_per_min": {"raw": 4.628230616302187, "pct": 0.9180327868852459}, "hero_damage_per_min": {"raw": 1358.314115308151, "pct": 0.9976580796252927}, "hero_healing_per_min": {"raw": 24.882703777335983, "pct": 0.234192037470726}, "tower_damage": {"raw": 3626, "pct": 0.9765807962529274}, "stuns_per_min": {"raw": 0, "pct": 0.09133489461358314}, "lhten": {}}}, {"match_id": 6514169966, "player_slot": 132, "ability_targets": null, "ability_upgrades_arr": [5458, 5460, 5458, 5459, 5458, 5461, 5459, 5459, 5459, 6368, 5460, 5461, 5460, 5460, 517, 5458, 5461, 6812], "ability_uses": null, "account_id": null, "actions": null, "additional_units": null, "assists": 25, "backpack_0": 0, "backpack_1": 0, "backpack_2": 0, "backpack_3": null, "buyback_log": null, "camps_stacked": null, "connection_log": null, "creeps_stacked": null, "damage": null, "damage_inflictor": null, "damage_inflictor_received": null, "damage_taken": null, "damage_targets": null, "deaths": 11, "denies": 2, "dn_t": null, "firstblood_claimed": null, "gold": 2915, "gold_per_min": 371, "gold_reasons": null, "gold_spent": 12675, "gold_t": null, "hero_damage": 16141, "hero_healing": 780, "hero_hits": null, "hero_id": 87, "item_0": 40, "item_1": 48, "item_2": 108, "item_3": 36, "item_4": 218, "item_5": 232, "item_neutral": 571, "item_uses": null, "kill_streaks": null, "killed": null, "killed_by": null, "kills": 6, "kills_log": null, "lane_pos": null, "last_hits": 74, "leaver_status": 0, "level": 24, "lh_t": null, "life_state": null, "max_hero_hit": null, "multi_kills": null, "net_worth": 12490, "obs": null, "obs_left_log": null, "obs_log": null, "obs_placed": null, "party_id": 9, "party_size": 1, "performance_others": null, "permanent_buffs": [{"permanent_buff": 6, "stack_count": 1}], "pings": null, "pred_vict": null, "purchase": null, "purchase_log": null, "randomed": null, "repicked": null, "roshans_killed": null, "rune_pickups": null, "runes": null, "runes_log": null, "sen": null, "sen_left_log": null, "sen_log": null, "sen_placed": null, "stuns": null, "teamfight_participation": null, "times": null, "tower_damage": 324, "towers_killed": null, "xp_per_min": 644, "xp_reasons": null, "xp_t": null, "radiant_win": false, "start_time": 1649387496, "duration": 2515, "cluster": 202, "lobby_type": 7, "game_mode": 22, "is_contributor": false, "patch": 50, "region": 10, "isRadiant": false, "win": 1, "lose": 0, "total_gold": 15551, "total_xp": 26994, "kills_per_min": 0.14314115308151093, "kda": 2, "abandons": 0, "rank_tier": null, "cosmetics": [], "benchmarks": {"gold_per_min": {"raw": 371, "pct": 0.8989769820971867}, "xp_per_min": {"raw": 644, "pct": 0.9207161125319693}, "kills_per_min": {"raw": 0.14314115308151096, "pct": 0.789002557544757}, "last_hits_per_min": {"raw": 1.765407554671968, "pct": 0.8542199488491049}, "hero_damage_per_min": {"raw": 385.0735586481113, "pct": 0.6176470588235294}, "hero_healing_per_min": {"raw": 18.608349900596423, "pct": 0.8222506393861893}, "tower_damage": {"raw": 324, "pct": 0.5869565217391305}, "stuns_per_min": {"raw": 0, "pct": 0.9526854219948849}, "lhten": {}}}], "patch": 50, "region": 10, "replay_url": "http://replay202.valve.net/570/6514169966_630476652.dem.bz2"}