{"match_id": 6514174740, "barracks_status_dire": 3, "barracks_status_radiant": 63, "chat": null, "cluster": 251, "cosmetics": null, "dire_score": 34, "dire_team_id": null, "draft_timings": null, "duration": 2573, "engine": 1, "first_blood_time": 187, "game_mode": 22, "human_players": 10, "leagueid": 0, "lobby_type": 7, "match_seq_num": 5441616616, "negative_votes": 0, "objectives": null, "picks_bans": [{"is_pick": true, "hero_id": 25, "team": 0, "order": 0}, {"is_pick": true, "hero_id": 27, "team": 1, "order": 1}, {"is_pick": true, "hero_id": 14, "team": 0, "order": 2}, {"is_pick": true, "hero_id": 19, "team": 1, "order": 3}, {"is_pick": true, "hero_id": 62, "team": 0, "order": 4}, {"is_pick": true, "hero_id": 94, "team": 0, "order": 5}, {"is_pick": true, "hero_id": 98, "team": 1, "order": 6}, {"is_pick": true, "hero_id": 47, "team": 1, "order": 7}, {"is_pick": true, "hero_id": 59, "team": 1, "order": 8}, {"is_pick": true, "hero_id": 34, "team": 0, "order": 9}, {"is_pick": false, "hero_id": 13, "team": 0, "order": 10}, {"is_pick": false, "hero_id": 70, "team": 0, "order": 11}, {"is_pick": false, "hero_id": 93, "team": 0, "order": 12}], "positive_votes": 0, "radiant_gold_adv": null, "radiant_score": 35, "radiant_team_id": null, "radiant_win": true, "radiant_xp_adv": null, "skill": null, "start_time": 1649387921, "teamfights": null, "tower_status_dire": 6, "tower_status_radiant": 1796, "version": null, "replay_salt": 1306697489, "series_id": 0, "series_type": 0, "players": [{"match_id": 6514174740, "player_slot": 0, "ability_targets": null, "ability_upgrades_arr": [5075, 5076, 5075, 5076, 5075, 5077, 5076, 5075, 5076, 5931, 5077, 5074, 5074, 5074, 5074, 507, 5077, 332], "ability_uses": null, "account_id": null, "actions": null, "additional_units": null, "assists": 17, "backpack_0": 34, "backpack_1": 0, "backpack_2": 0, "backpack_3": null, "buyback_log": null, "camps_stacked": null, "connection_log": null, "creeps_stacked": null, "damage": null, "damage_inflictor": null, "damage_inflictor_received": null, "damage_taken": null, "damage_targets": null, "deaths": 8, "denies": 2, "dn_t": null, "firstblood_claimed": null, "gold": 2264, "gold_per_min": 318, "gold_reasons": null, "gold_spent": 11425, "gold_t": null, "hero_damage": 13436, "hero_healing": 1447, "hero_hits": null, "hero_id": 14, "item_0": 178, "item_1": 254, "item_2": 214, "item_3": 218, "item_4": 232, "item_5": 102, "item_neutral": 335, "item_uses": null, "kill_streaks": null, "killed": null, "killed_by": null, "kills": 3, "kills_log": null, "lane_pos": null, "last_hits": 34, "leaver_status": 0, "level": 22, "lh_t": null, "life_state": null, "max_hero_hit": null, "multi_kills": null, "net_worth": 12014, "obs": null, "obs_left_log": null, "obs_log": null, "obs_placed": null, "party_id": 0, "party_size": 1, "performance_others": null, "permanent_buffs": [{"permanent_buff": 4, "stack_count": 12}, {"permanent_buff": 6, "stack_count": 1}, {"permanent_buff": 12, "stack_count": 0}], "pings": null, "pred_vict": null, "purchase": null, "purchase_log": null, "randomed": null, "repicked": null, "roshans_killed": null, "rune_pickups": null, "runes": null, "runes_log": null, "sen": null, "sen_left_log": null, "sen_log": null, "sen_placed": null, "stuns": null, "teamfight_participation": null, "times": null, "tower_damage": 302, "towers_killed": null, "xp_per_min": 540, "xp_reasons": null, "xp_t": null, "radiant_win": true, "start_time": 1649387921, "duration": 2573, "cluster": 251, "lobby_type": 7, "game_mode": 22, "is_contributor": false, "patch": 50, "region": 15, "isRadiant": true, "win": 1, "lose": 0, "total_gold": 13636, "total_xp": 23157, "kills_per_min": 0.06995724834823164, "kda": 2, "abandons": 0, "rank_tier": null, "cosmetics": [], "benchmarks": {"gold_per_min": {"raw": 318, "pct": 0.42074592074592077}, "xp_per_min": {"raw": 540, "pct": 0.5777000777000777}, "kills_per_min": {"raw": 0.06995724834823164, "pct": 0.17560217560217561}, "last_hits_per_min": {"raw": 0.7928488146132919, "pct": 0.1320901320901321}, "hero_damage_per_min": {"raw": 313.31519626894675, "pct": 0.23232323232323232}, "hero_healing_per_min": {"raw": 33.74271278663039, "pct": 0.8344988344988346}, "tower_damage": {"raw": 302, "pct": 0.5796425796425796}, "stuns_per_min": {"raw": 0, "pct": 0.0003885003885003885}, "lhten": {}}}, {"match_id": 6514174740, "player_slot": 1, "ability_targets": null, "ability_upgrades_arr": [5286, 5285, 5286, 5287, 5286, 5288, 5286, 5285, 5285, 484, 5285, 5288, 5287, 5287, 6358, 5287, 5288, 878, 877], "ability_uses": null, "account_id": null, "actions": null, "additional_units": null, "assists": 20, "backpack_0": 57, "backpack_1": 0, "backpack_2": 0, "backpack_3": null, "buyback_log": null, "camps_stacked": null, "connection_log": null, "creeps_stacked": null, "damage": null, "damage_inflictor": null, "damage_inflictor_received": null, "damage_taken": null, "damage_targets": null, "deaths": 6, "denies": 12, "dn_t": null, "firstblood_claimed": null, "gold": 6831, "gold_per_min": 573, "gold_reasons": null, "gold_spent": 17700, "gold_t": null, "hero_damage": 33393, "hero_healing": 0, "hero_hits": null, "hero_id": 62, "item_0": 123, "item_1": 108, "item_2": 36, "item_3": 267, "item_4": 50, "item_5": 24, "item_neutral": 361, "item_uses": null, "kill_streaks": null, "killed": null, "killed_by": null, "kills": 6, "kills_log": null, "lane_pos": null, "last_hits": 94, "leaver_status": 0, "level": 25, "lh_t": null, "life_state": null, "max_hero_hit": null, "multi_kills": null, "net_worth": 23396, "obs": null, "obs_left_log": null, "obs_log": null, "obs_placed": null, "party_id": 1, "party_size": 1, "performance_others": null, "permanent_buffs": [{"permanent_buff": 10, "stack_count": 2323}], "pings": null, "pred_vict": null, "purchase": null, "purchase_log": null, "randomed": null, "repicked": null, "roshans_killed": null, "rune_pickups": null, "runes": null, "runes_log": null, "sen": null, "sen_left_log": null, "sen_log": null, "sen_placed": null, "stuns": null, "teamfight_participation": null, "times": null, "tower_damage": 4438, "towers_killed": null, "xp_per_min": 674, "xp_reasons": null, "xp_t": null, "radiant_win": true, "start_time": 1649387921, "duration": 2573, "cluster": 251, "lobby_type": 7, "game_mode": 22, "is_contributor": false, "patch": 50, "region": 15, "isRadiant": true, "win": 1, "lose": 0, "total_gold": 24572, "total_xp": 28903, "kills_per_min": 0.13991449669646328, "kda": 3, "abandons": 0, "rank_tier": null, "cosmetics": [], "benchmarks": {"gold_per_min": {"raw": 573, "pct": 0.7652284263959391}, "xp_per_min": {"raw": 674, "pct": 0.7715736040609137}, "kills_per_min": {"raw": 0.13991449669646328, "pct": 0.4200507614213198}, "last_hits_per_min": {"raw": 2.1919937815779242, "pct": 0.7423857868020305}, "hero_damage_per_min": {"raw": 778.6941313641664, "pct": 0.7969543147208121}, "hero_healing_per_min": {"raw": 0, "pct": 0.7284263959390863}, "tower_damage": {"raw": 4438, "pct": 0.949238578680203}, "stuns_per_min": {"raw": 0, "pct": 0.005076142131979695}, "lhten": {}}}, {"match_id": 6514174740, "player_slot": 2, "ability_targets": null, "ability_upgrades_arr": [5041, 5042, 5040, 5042, 5040, 5043, 5040, 5040, 5042, 6009, 5042, 5043, 5041, 5041, 6195, 5041, 5043, 444], "ability_uses": null, "account_id": null, "actions": null, "additional_units": null, "assists": 10, "backpack_0": 0, "backpack_1": 0, "backpack_2": 38, "backpack_3": null, "buyback_log": null, "camps_stacked": null, "connection_log": null, "creeps_stacked": null, "damage": null, "damage_inflictor": null, "damage_inflictor_received": null, "damage_taken": null, "damage_targets": null, "deaths": 8, "denies": 4, "dn_t": null, "firstblood_claimed": null, "gold": 3733, "gold_per_min": 464, "gold_reasons": null, "gold_spent": 16180, "gold_t": null, "hero_damage": 25112, "hero_healing": 0, "hero_hits": null, "hero_id": 25, "item_0": 43, "item_1": 244, "item_2": 48, "item_3": 141, "item_4": 77, "item_5": 249, "item_neutral": 379, "item_uses": null, "kill_streaks": null, "killed": null, "killed_by": null, "kills": 8, "kills_log": null, "lane_pos": null, "last_hits": 170, "leaver_status": 0, "level": 24, "lh_t": null, "life_state": null, "max_hero_hit": null, "multi_kills": null, "net_worth": 17688, "obs": null, "obs_left_log": null, "obs_log": null, "obs_placed": null, "party_id": 2, "party_size": 2, "performance_others": null, "permanent_buffs": [{"permanent_buff": 6, "stack_count": 3}], "pings": null, "pred_vict": null, "purchase": null, "purchase_log": null, "randomed": null, "repicked": null, "roshans_killed": null, "rune_pickups": null, "runes": null, "runes_log": null, "sen": null, "sen_left_log": null, "sen_log": null, "sen_placed": null, "stuns": null, "teamfight_participation": null, "times": null, "tower_damage": 6710, "towers_killed": null, "xp_per_min": 611, "xp_reasons": null, "xp_t": null, "radiant_win": true, "start_time": 1649387921, "duration": 2573, "cluster": 251, "lobby_type": 7, "game_mode": 22, "is_contributor": false, "patch": 50, "region": 15, "isRadiant": true, "win": 1, "lose": 0, "total_gold": 19897, "total_xp": 26201, "kills_per_min": 0.18655266226195102, "kda": 2, "abandons": 0, "rank_tier": null, "cosmetics": [], "benchmarks": {"gold_per_min": {"raw": 464, "pct": 0.4525345622119816}, "xp_per_min": {"raw": 611, "pct": 0.40184331797235023}, "kills_per_min": {"raw": 0.18655266226195102, "pct": 0.45161290322580644}, "last_hits_per_min": {"raw": 3.964244073066459, "pct": 0.3585253456221198}, "hero_damage_per_min": {"raw": 585.5888068402643, "pct": 0.4949308755760369}, "hero_healing_per_min": {"raw": 0, "pct": 0.7797235023041474}, "tower_damage": {"raw": 6710, "pct": 0.6930875576036867}, "stuns_per_min": {"raw": 0, "pct": 0.0009216589861751152}, "lhten": {}}}, {"match_id": 6514174740, "player_slot": 3, "ability_targets": null, "ability_upgrades_arr": [5505, 5506, 5505, 5506, 5505, 5507, 5505, 5506, 5506, 920, 5504, 5507, 5504, 5504, 6392, 5504, 5507, 6182, 6803], "ability_uses": null, "account_id": 123455744, "actions": null, "additional_units": null, "assists": 17, "backpack_0": 0, "backpack_1": 0, "backpack_2": 0, "backpack_3": null, "buyback_log": null, "camps_stacked": null, "connection_log": null, "creeps_stacked": null, "damage": null, "damage_inflictor": null, "damage_inflictor_received": null, "damage_taken": null, "damage_targets": null, "deaths": 6, "denies": 8, "dn_t": null, "firstblood_claimed": null, "gold": 2044, "gold_per_min": 665, "gold_reasons": null, "gold_spent": 25835, "gold_t": null, "hero_damage": 39011, "hero_healing": 0, "hero_hits": null, "hero_id": 94, "item_0": 63, "item_1": 158, "item_2": 75, "item_3": 147, "item_4": 160, "item_5": 263, "item_neutral": 585, "item_uses": null, "kill_streaks": null, "killed": null, "killed_by": null, "kills": 4, "kills_log": null, "lane_pos": null, "last_hits": 381, "leaver_status": 0, "level": 26, "lh_t": null, "life_state": null, "max_hero_hit": null, "multi_kills": null, "net_worth": 26874, "obs": null, "obs_left_log": null, "obs_log": null, "obs_placed": null, "party_id": 2, "party_size": 2, "performance_others": null, "permanent_buffs": [], "pings": null, "pred_vict": null, "purchase": null, "purchase_log": null, "randomed": null, "repicked": null, "roshans_killed": null, "rune_pickups": null, "runes": null, "runes_log": null, "sen": null, "sen_left_log": null, "sen_log": null, "sen_placed": null, "stuns": null, "teamfight_participation": null, "times": null, "tower_damage": 12060, "towers_killed": null, "xp_per_min": 707, "xp_reasons": null, "xp_t": null, "personaname": "AlaPrimasearrimagiordota.com", "name": null, "last_login": null, "radiant_win": true, "start_time": 1649387921, "duration": 2573, "cluster": 251, "lobby_type": 7, "game_mode": 22, "is_contributor": false, "patch": 50, "region": 15, "isRadiant": true, "win": 1, "lose": 0, "total_gold": 28517, "total_xp": 30318, "kills_per_min": 0.09327633113097551, "kda": 3, "abandons": 0, "rank_tier": 34, "cosmetics": [], "benchmarks": {"gold_per_min": {"raw": 665, "pct": 0.5392934390771449}, "xp_per_min": {"raw": 707, "pct": 0.35039653929343906}, "kills_per_min": {"raw": 0.09327633113097551, "pct": 0.2927180966113915}, "last_hits_per_min": {"raw": 8.884570540225418, "pct": 0.3705839942321557}, "hero_damage_per_min": {"raw": 909.7007384376215, "pct": 0.7332372025955299}, "hero_healing_per_min": {"raw": 0, "pct": 0.9863013698630136}, "tower_damage": {"raw": 12060, "pct": 0.6928622927180966}, "stuns_per_min": {"raw": 0, "pct": 0.04253785147801009}, "lhten": {}}}, {"match_id": 6514174740, "player_slot": 4, "ability_targets": null, "ability_upgrades_arr": [5150, 5151, 5151, 5150, 5150, 5151, 5153, 5151, 5150, 650, 650, 5153, 650, 650, 7898, 8039, 5153, 5989, 6953, 800], "ability_uses": null, "account_id": 148927798, "actions": null, "additional_units": null, "assists": 19, "backpack_0": 606, "backpack_1": 0, "backpack_2": 0, "backpack_3": null, "buyback_log": null, "camps_stacked": null, "connection_log": null, "creeps_stacked": null, "damage": null, "damage_inflictor": null, "damage_inflictor_received": null, "damage_taken": null, "damage_targets": null, "deaths": 6, "denies": 5, "dn_t": null, "firstblood_claimed": null, "gold": 307, "gold_per_min": 507, "gold_reasons": null, "gold_spent": 20000, "gold_t": null, "hero_damage": 75854, "hero_healing": 0, "hero_hits": null, "hero_id": 34, "item_0": 1, "item_1": 96, "item_2": 37, "item_3": 178, "item_4": 108, "item_5": 232, "item_neutral": 589, "item_uses": null, "kill_streaks": null, "killed": null, "killed_by": null, "kills": 11, "kills_log": null, "lane_pos": null, "last_hits": 154, "leaver_status": 0, "level": 27, "lh_t": null, "life_state": null, "max_hero_hit": null, "multi_kills": null, "net_worth": 18757, "obs": null, "obs_left_log": null, "obs_log": null, "obs_placed": null, "party_id": 3, "party_size": 1, "performance_others": null, "permanent_buffs": [], "pings": null, "pred_vict": null, "purchase": null, "purchase_log": null, "randomed": null, "repicked": null, "roshans_killed": null, "rune_pickups": null, "runes": null, "runes_log": null, "sen": null, "sen_left_log": null, "sen_log": null, "sen_placed": null, "stuns": null, "teamfight_participation": null, "times": null, "tower_damage": 157, "towers_killed": null, "xp_per_min": 762, "xp_reasons": null, "xp_t": null, "personaname": "chollapse uwu", "name": null, "last_login": null, "radiant_win": true, "start_time": 1649387921, "duration": 2573, "cluster": 251, "lobby_type": 7, "game_mode": 22, "is_contributor": false, "patch": 50, "region": 15, "isRadiant": true, "win": 1, "lose": 0, "total_gold": 21741, "total_xp": 32677, "kills_per_min": 0.2565099106101827, "kda": 4, "abandons": 0, "rank_tier": 34, "cosmetics": [], "benchmarks": {"gold_per_min": {"raw": 507, "pct": 0.5913978494623656}, "xp_per_min": {"raw": 762, "pct": 0.6602150537634408}, "kills_per_min": {"raw": 0.2565099106101827, "pct": 0.621505376344086}, "last_hits_per_min": {"raw": 3.591138748542557, "pct": 0.34408602150537637}, "hero_damage_per_min": {"raw": 1768.8457054022542, "pct": 0.9720430107526882}, "hero_healing_per_min": {"raw": 0, "pct": 0.7118279569892473}, "tower_damage": {"raw": 157, "pct": 0.6150537634408603}, "stuns_per_min": {"raw": 0, "pct": 0.5612903225806452}, "lhten": {}}}, {"match_id": 6514174740, "player_slot": 128, "ability_targets": null, "ability_upgrades_arr": [5080, 5079, 5080, 5079, 5080, 5081, 5079, 5078, 5080, 5079, 5078, 5081, 5078, 5078, 6295, 6877, 5081, 760], "ability_uses": null, "account_id": null, "actions": null, "additional_units": null, "assists": 15, "backpack_0": 16, "backpack_1": 0, "backpack_2": 0, "backpack_3": null, "buyback_log": null, "camps_stacked": null, "connection_log": null, "creeps_stacked": null, "damage": null, "damage_inflictor": null, "damage_inflictor_received": null, "damage_taken": null, "damage_targets": null, "deaths": 10, "denies": 0, "dn_t": null, "firstblood_claimed": null, "gold": 1037, "gold_per_min": 253, "gold_reasons": null, "gold_spent": 9045, "gold_t": null, "hero_damage": 8010, "hero_healing": 0, "hero_hits": null, "hero_id": 27, "item_0": 1, "item_1": 214, "item_2": 42, "item_3": 232, "item_4": 40, "item_5": 260, "item_neutral": 326, "item_uses": null, "kill_streaks": null, "killed": null, "killed_by": null, "kills": 2, "kills_log": null, "lane_pos": null, "last_hits": 37, "leaver_status": 0, "level": 20, "lh_t": null, "life_state": null, "max_hero_hit": null, "multi_kills": null, "net_worth": 8217, "obs": null, "obs_left_log": null, "obs_log": null, "obs_placed": null, "party_id": 4, "party_size": 2, "performance_others": null, "permanent_buffs": [{"permanent_buff": 12, "stack_count": 0}], "pings": null, "pred_vict": null, "purchase": null, "purchase_log": null, "randomed": null, "repicked": null, "roshans_killed": null, "rune_pickups": null, "runes": null, "runes_log": null, "sen": null, "sen_left_log": null, "sen_log": null, "sen_placed": null, "stuns": null, "teamfight_participation": null, "times": null, "tower_damage": 590, "towers_killed": null, "xp_per_min": 430, "xp_reasons": null, "xp_t": null, "radiant_win": true, "start_time": 1649387921, "duration": 2573, "cluster": 251, "lobby_type": 7, "game_mode": 22, "is_contributor": false, "patch": 50, "region": 15, "isRadiant": false, "win": 0, "lose": 1, "total_gold": 10849, "total_xp": 18439, "kills_per_min": 0.046638165565487756, "kda": 1, "abandons": 0, "rank_tier": null, "cosmetics": [], "benchmarks": {"gold_per_min": {"raw": 253, "pct": 0.162217659137577}, "xp_per_min": {"raw": 430, "pct": 0.40999315537303216}, "kills_per_min": {"raw": 0.046638165565487756, "pct": 0.23408624229979466}, "last_hits_per_min": {"raw": 0.8628060629615235, "pct": 0.11430527036276524}, "hero_damage_per_min": {"raw": 186.78585308977847, "pct": 0.10061601642710473}, "hero_healing_per_min": {"raw": 0, "pct": 0.5017111567419575}, "tower_damage": {"raw": 590, "pct": 0.26967830253251196}, "stuns_per_min": {"raw": 0, "pct": 0}, "lhten": {}}}, {"match_id": 6514174740, "player_slot": 129, "ability_targets": null, "ability_upgrades_arr": [5525, 5526, 5526, 5525, 5526, 5527, 5526, 5525, 5525, 5524, 5524, 5527, 5524, 5524, 7132, 5949, 5527, 6951], "ability_uses": null, "account_id": 913269052, "actions": null, "additional_units": null, "assists": 9, "backpack_0": 0, "backpack_1": 0, "backpack_2": 0, "backpack_3": null, "buyback_log": null, "camps_stacked": null, "connection_log": null, "creeps_stacked": null, "damage": null, "damage_inflictor": null, "damage_inflictor_received": null, "damage_taken": null, "damage_targets": null, "deaths": 8, "denies": 13, "dn_t": null, "firstblood_claimed": null, "gold": 686, "gold_per_min": 403, "gold_reasons": null, "gold_spent": 15145, "gold_t": null, "hero_damage": 32086, "hero_healing": 0, "hero_hits": null, "hero_id": 98, "item_0": 178, "item_1": 692, "item_2": 226, "item_3": 73, "item_4": 29, "item_5": 273, "item_neutral": 825, "item_uses": null, "kill_streaks": null, "killed": null, "killed_by": null, "kills": 6, "kills_log": null, "lane_pos": null, "last_hits": 178, "leaver_status": 0, "level": 23, "lh_t": null, "life_state": null, "max_hero_hit": null, "multi_kills": null, "net_worth": 15141, "obs": null, "obs_left_log": null, "obs_log": null, "obs_placed": null, "party_id": 4, "party_size": 2, "performance_others": null, "permanent_buffs": [{"permanent_buff": 6, "stack_count": 2}, {"permanent_buff": 12, "stack_count": 0}], "pings": null, "pred_vict": null, "purchase": null, "purchase_log": null, "randomed": null, "repicked": null, "roshans_killed": null, "rune_pickups": null, "runes": null, "runes_log": null, "sen": null, "sen_left_log": null, "sen_log": null, "sen_placed": null, "stuns": null, "teamfight_participation": null, "times": null, "tower_damage": 555, "towers_killed": null, "xp_per_min": 554, "xp_reasons": null, "xp_t": null, "personaname": "Dikkman", "name": null, "last_login": null, "radiant_win": true, "start_time": 1649387921, "duration": 2573, "cluster": 251, "lobby_type": 7, "game_mode": 22, "is_contributor": false, "patch": 50, "region": 15, "isRadiant": false, "win": 0, "lose": 1, "total_gold": 17281, "total_xp": 23757, "kills_per_min": 0.13991449669646328, "kda": 1, "abandons": 0, "rank_tier": 34, "cosmetics": [], "benchmarks": {"gold_per_min": {"raw": 403, "pct": 0.3333333333333333}, "xp_per_min": {"raw": 554, "pct": 0.36507936507936506}, "kills_per_min": {"raw": 0.13991449669646328, "pct": 0.35714285714285715}, "last_hits_per_min": {"raw": 4.15079673532841, "pct": 0.38095238095238093}, "hero_damage_per_min": {"raw": 748.2160901671201, "pct": 0.6984126984126984}, "hero_healing_per_min": {"raw": 0, "pct": 0.9365079365079365}, "tower_damage": {"raw": 555, "pct": 0.3630952380952381}, "stuns_per_min": {"raw": 0, "pct": 0.5555555555555556}, "lhten": {}}}, {"match_id": 6514174740, "player_slot": 130, "ability_targets": null, "ability_upgrades_arr": [5108, 5106, 5107, 5108, 6937, 5109, 6937, 5106, 5106, 6137, 5106, 5109, 5107, 5107, 718, 5107, 5109, 6122], "ability_uses": null, "account_id": null, "actions": null, "additional_units": null, "assists": 6, "backpack_0": 21, "backpack_1": 75, "backpack_2": 0, "backpack_3": null, "buyback_log": null, "camps_stacked": null, "connection_log": null, "creeps_stacked": null, "damage": null, "damage_inflictor": null, "damage_inflictor_received": null, "damage_taken": null, "damage_targets": null, "deaths": 5, "denies": 0, "dn_t": null, "firstblood_claimed": null, "gold": 432, "gold_per_min": 416, "gold_reasons": null, "gold_spent": 17020, "gold_t": null, "hero_damage": 10711, "hero_healing": 189, "hero_hits": null, "hero_id": 19, "item_0": 1, "item_1": 112, "item_2": 29, "item_3": 252, "item_4": 8, "item_5": 218, "item_neutral": 638, "item_uses": null, "kill_streaks": null, "killed": null, "killed_by": null, "kills": 2, "kills_log": null, "lane_pos": null, "last_hits": 223, "leaver_status": 0, "level": 23, "lh_t": null, "life_state": null, "max_hero_hit": null, "multi_kills": null, "net_worth": 15562, "obs": null, "obs_left_log": null, "obs_log": null, "obs_placed": null, "party_id": 5, "party_size": 2, "performance_others": null, "permanent_buffs": [{"permanent_buff": 6, "stack_count": 2}, {"permanent_buff": 12, "stack_count": 0}], "pings": null, "pred_vict": null, "purchase": null, "purchase_log": null, "randomed": null, "repicked": null, "roshans_killed": null, "rune_pickups": null, "runes": null, "runes_log": null, "sen": null, "sen_left_log": null, "sen_log": null, "sen_placed": null, "stuns": null, "teamfight_participation": null, "times": null, "tower_damage": 1900, "towers_killed": null, "xp_per_min": 557, "xp_reasons": null, "xp_t": null, "radiant_win": true, "start_time": 1649387921, "duration": 2573, "cluster": 251, "lobby_type": 7, "game_mode": 22, "is_contributor": false, "patch": 50, "region": 15, "isRadiant": false, "win": 0, "lose": 1, "total_gold": 17839, "total_xp": 23886, "kills_per_min": 0.046638165565487756, "kda": 1, "abandons": 0, "rank_tier": null, "cosmetics": [], "benchmarks": {"gold_per_min": {"raw": 416, "pct": 0.14796425024826215}, "xp_per_min": {"raw": 557, "pct": 0.1608738828202582}, "kills_per_min": {"raw": 0.046638165565487756, "pct": 0.0650446871896723}, "last_hits_per_min": {"raw": 5.200155460551885, "pct": 0.16981132075471697}, "hero_damage_per_min": {"raw": 249.77069568596968, "pct": 0.03426017874875869}, "hero_healing_per_min": {"raw": 4.4073066459385934, "pct": 0.9731876861966237}, "tower_damage": {"raw": 1900, "pct": 0.2671300893743793}, "stuns_per_min": {"raw": 0, "pct": 0}, "lhten": {}}}, {"match_id": 6514174740, "player_slot": 131, "ability_targets": null, "ability_upgrades_arr": [5218, 5219, 5219, 5218, 5218, 5221, 5218, 5219, 5219, 6156, 5220, 5221, 5220, 5220, 5993, 5220, 5221, 6165, 645], "ability_uses": null, "account_id": null, "actions": null, "additional_units": null, "assists": 4, "backpack_0": 36, "backpack_1": 40, "backpack_2": 0, "backpack_3": null, "buyback_log": null, "camps_stacked": null, "connection_log": null, "creeps_stacked": null, "damage": null, "damage_inflictor": null, "damage_inflictor_received": null, "damage_taken": null, "damage_targets": null, "deaths": 3, "denies": 7, "dn_t": null, "firstblood_claimed": null, "gold": 1278, "gold_per_min": 561, "gold_reasons": null, "gold_spent": 21950, "gold_t": null, "hero_damage": 20086, "hero_healing": 0, "hero_hits": null, "hero_id": 47, "item_0": 114, "item_1": 263, "item_2": 23, "item_3": 166, "item_4": 135, "item_5": 63, "item_neutral": 376, "item_uses": null, "kill_streaks": null, "killed": null, "killed_by": null, "kills": 9, "kills_log": null, "lane_pos": null, "last_hits": 322, "leaver_status": 0, "level": 26, "lh_t": null, "life_state": null, "max_hero_hit": null, "multi_kills": null, "net_worth": 21533, "obs": null, "obs_left_log": null, "obs_log": null, "obs_placed": null, "party_id": 5, "party_size": 2, "performance_others": null, "permanent_buffs": [], "pings": null, "pred_vict": null, "purchase": null, "purchase_log": null, "randomed": null, "repicked": null, "roshans_killed": null, "rune_pickups": null, "runes": null, "runes_log": null, "sen": null, "sen_left_log": null, "sen_log": null, "sen_placed": null, "stuns": null, "teamfight_participation": null, "times": null, "tower_damage": 4060, "towers_killed": null, "xp_per_min": 696, "xp_reasons": null, "xp_t": null, "radiant_win": true, "start_time": 1649387921, "duration": 2573, "cluster": 251, "lobby_type": 7, "game_mode": 22, "is_contributor": false, "patch": 50, "region": 15, "isRadiant": false, "win": 0, "lose": 1, "total_gold": 24057, "total_xp": 29846, "kills_per_min": 0.2098717450446949, "kda": 3, "abandons": 0, "rank_tier": null, "cosmetics": [], "benchmarks": {"gold_per_min": {"raw": 561, "pct": 0.8269230769230769}, "xp_per_min": {"raw": 696, "pct": 0.6983805668016194}, "kills_per_min": {"raw": 0.2098717450446949, "pct": 0.5060728744939271}, "last_hits_per_min": {"raw": 7.508744656043528, "pct": 0.9625506072874493}, "hero_damage_per_min": {"raw": 468.38709677419354, "pct": 0.15688259109311742}, "hero_healing_per_min": {"raw": 0, "pct": 0.8410931174089069}, "tower_damage": {"raw": 4060, "pct": 0.6103238866396761}, "stuns_per_min": {"raw": 0, "pct": 0.667004048582996}, "lhten": {}}}, {"match_id": 6514174740, "player_slot": 132, "ability_targets": null, "ability_upgrades_arr": [5272, 5273, 5272, 5273, 5273, 5274, 5273, 5272, 5272, 7300, 6655, 5274, 7300, 7300, 7300, 6289, 5274, 462, 6204], "ability_uses": null, "account_id": 848178000, "actions": null, "additional_units": null, "assists": 3, "backpack_0": 33, "backpack_1": 115, "backpack_2": 0, "backpack_3": null, "buyback_log": null, "camps_stacked": null, "connection_log": null, "creeps_stacked": null, "damage": null, "damage_inflictor": null, "damage_inflictor_received": null, "damage_taken": null, "damage_targets": null, "deaths": 10, "denies": 17, "dn_t": null, "firstblood_claimed": null, "gold": 351, "gold_per_min": 497, "gold_reasons": null, "gold_spent": 19225, "gold_t": null, "hero_damage": 30089, "hero_healing": 0, "hero_hits": null, "hero_id": 59, "item_0": 1, "item_1": 108, "item_2": 151, "item_3": 226, "item_4": 63, "item_5": 8, "item_neutral": 379, "item_uses": null, "kill_streaks": null, "killed": null, "killed_by": null, "kills": 15, "kills_log": null, "lane_pos": null, "last_hits": 200, "leaver_status": 0, "level": 25, "lh_t": null, "life_state": null, "max_hero_hit": null, "multi_kills": null, "net_worth": 20081, "obs": null, "obs_left_log": null, "obs_log": null, "obs_placed": null, "party_id": 6, "party_size": 1, "performance_others": null, "permanent_buffs": [{"permanent_buff": 12, "stack_count": 0}], "pings": null, "pred_vict": null, "purchase": null, "purchase_log": null, "randomed": null, "repicked": null, "roshans_killed": null, "rune_pickups": null, "runes": null, "runes_log": null, "sen": null, "sen_left_log": null, "sen_log": null, "sen_placed": null, "stuns": null, "teamfight_participation": null, "times": null, "tower_damage": 3907, "towers_killed": null, "xp_per_min": 707, "xp_reasons": null, "xp_t": null, "personaname": "GRECITA", "name": null, "last_login": null, "radiant_win": true, "start_time": 1649387921, "duration": 2573, "cluster": 251, "lobby_type": 7, "game_mode": 22, "is_contributor": false, "patch": 50, "region": 15, "isRadiant": false, "win": 0, "lose": 1, "total_gold": 21313, "total_xp": 30318, "kills_per_min": 0.3497862417411582, "kda": 1, "abandons": 0, "rank_tier": 35, "cosmetics": [], "benchmarks": {"gold_per_min": {"raw": 497, "pct": 0.5095194922937444}, "xp_per_min": {"raw": 707, "pct": 0.6183136899365367}, "kills_per_min": {"raw": 0.3497862417411582, "pct": 0.6935630099728014}, "last_hits_per_min": {"raw": 4.663816556548776, "pct": 0.45602901178603805}, "hero_damage_per_min": {"raw": 701.6478818499805, "pct": 0.4315503173164098}, "hero_healing_per_min": {"raw": 0, "pct": 0.9927470534904805}, "tower_damage": {"raw": 3907, "pct": 0.4814143245693563}, "stuns_per_min": {"raw": 0, "pct": 0.9737080689029919}, "lhten": {}}}], "patch": 50, "region": 15, "replay_url": "http://replay251.valve.net/570/6514174740_1306697489.dem.bz2"}